{
    "id": 4526567,
    "judges": "Per Curiam",
    "date_filed": "1995-02-24",
    "date_filed_is_approximate": true,
    "slug": "rodrigo-ramos-braga-v-jefferson-b-sessions-iii",
    "case_name_short": null,
    "case_name": "Rodrigo Ramos-Braga v. Jefferson B. Sessions III",
    "case_name_full": null,
    "attorneys": null,
    "nature_of_suit": "agency",
    "posture": null,
    "syllabus": null,
    "headnotes": null,
    "summary": null,
    "disposition": null,
    "history": null,
    "other_dates": null,
    "cross_reference": null,
    "correction": null,
    "citation_count": 0,
    "precedential_status": "Published",
    "arguments": null,
    "headmatter": null,
    "citations": null,
    "opinions": [
        {
            "author_str": null,
            "per_curiam": false,
            "type": "010combined",
            "page_count": 22.0,
            "download_url": "http://media.ca7.uscourts.gov/cgi-bin/rssExec.pl?Submit=Display&Path=Y2018/D08-14/C:17-1998:J:PerCuriam:aut:T:aOp:N:2202097:S:0",
            "author_id": null,
            "opinion_text": "\u00a0                                                                   \u00a0\n\n                              In the\n\n     United States Court of Appeals\n                For the Seventh Circuit\n                    ____________________\u00a0\nNo.\u00a017\u20101998\u00a0\nRODRIGO\u00a0RAMOS\u2010BRAGA,\u00a0\n                                                         Petitioner,\u00a0\n                                 v.\u00a0\n\nJEFFERSON\u00a0B.\u00a0SESSIONS\u00a0III,\u00a0\nAttorney\u00a0General\u00a0of\u00a0the\u00a0United\u00a0States,\u00a0\n                                                 \u00a0      Respondent.\u00a0\n                    ____________________\u00a0\n                 Petition\u00a0for\u00a0Review\u00a0of\u00a0an\u00a0Order\u00a0of\u00a0\u00a0\n                the\u00a0Board\u00a0of\u00a0Immigration\u00a0Appeals.\u00a0\n                         No.\u00a0A\u00a0097\u2010837\u2010809\u00a0\n                    ____________________\u00a0\n\n     ARGUED\u00a0JANUARY\u00a024,\u00a02018\u00a0\u2014\u00a0DECIDED\u00a0MAY\u00a021,\u00a02018\u00a0\n               AMENDED\u00a0AUGUST\u00a014,\u00a02018\u00a0\n                ____________________\u00a0\n\n    Before\u00a0BAUER,\u00a0KANNE,\u00a0and\u00a0BARRETT,\u00a0Circuit\u00a0Judges.\u00a0\n    PER\u00a0CURIAM.\u00a0\u00a0Rodrigo\u00a0Ramos\u2010Braga,\u00a0a\u00a0citizen\u00a0of\u00a0Brazil,\u00a0pe\u2010\ntitions\u00a0for\u00a0review\u00a0of\u00a0the\u00a0denial\u00a0of\u00a0his\u00a0second\u00a0motion\u00a0to\u00a0reopen\u00a0\nproceedings\u00a0on\u00a0 his\u00a0 applications\u00a0for\u00a0special\u2010rule\u00a0cancellation\u00a0\nof\u00a0removal,\u00a0withholding\u00a0of\u00a0removal,\u00a0and\u00a0protection\u00a0under\u00a0the\u00a0\nConvention\u00a0Against\u00a0Torture\u00a0(CAT).\u00a0His\u00a0motion\u00a0was\u00a0both\u00a0nu\u2010\n\f2\u00a0                                                    No.\u00a017\u20101998\u00a0\n\nmerically\u00a0barred\u00a0and\u00a0untimely\u00a0filed\u00a0with\u00a0the\u00a0Board\u00a0of\u00a0Immi\u2010\ngration\u00a0 Appeals,\u00a0 but\u00a0 Ramos\u2010Braga\u00a0 argued\u00a0 that\u00a0 these\u00a0 limits\u00a0\nshould\u00a0be\u00a0excused\u00a0under\u00a0the\u00a0doctrine\u00a0of\u00a0equitable\u00a0tolling\u00a0for\u00a0\nine\ufb00ective\u00a0 assistance\u00a0 of\u00a0 counsel\u00a0or\u00a0 under\u00a0 a\u00a0 statutory\u00a0 excep\u2010\ntion\u00a0based\u00a0on\u00a0changed\u00a0country\u00a0conditions.\u00a0The\u00a0Board\u00a0deter\u2010\nmined\u00a0 that\u00a0 neither\u00a0exception\u00a0 applied\u00a0and\u00a0 that\u00a0the\u00a0time\u00a0and\u00a0\nnumerical\u00a0 limits\u00a0 therefore\u00a0 barred\u00a0 his\u00a0 motion.\u00a0 Because\u00a0 the\u00a0\nBoard\u00a0did\u00a0not\u00a0abuse\u00a0its\u00a0discretion,\u00a0we\u00a0deny\u00a0the\u00a0petition.\u00a0\u00a0\n                                I.\u00a0\n     Ramos\u2010Braga\u00a0was\u00a0raised\u00a0in\u00a0a\u00a0neighborhood\u00a0of\u00a0S\u00e3o\u00a0Paulo,\u00a0\nBrazil\u00a0 that\u00a0 came\u00a0 to\u00a0 be\u00a0 controlled\u00a0 by\u00a0 a\u00a0 multi\u2010national\u00a0 gang\u00a0\nnamed\u00a0the\u00a0Primero\u00a0Comando\u00a0Capital\u00a0(PCC).\u00a0His\u00a0father\u00a0dealt\u00a0\ndrugs\u00a0for\u00a0the\u00a0gang\u00a0and\u00a0was\u00a0one\u00a0of\u00a0its\u00a0managers,\u00a0until\u00a0he\u00a0had\u00a0\na\u00a0 falling\u00a0 out\u00a0 with\u00a0 the\u00a0 gang\u2019s\u00a0 leader.\u00a0 Starting\u00a0 when\u00a0 Ramos\u2010\nBraga\u00a0was\u00a013,\u00a0the\u00a0PCC\u00a0tried\u00a0repeatedly\u00a0to\u00a0recruit\u00a0him,\u00a0but\u00a0he\u00a0\nrefused\u00a0 to\u00a0 join.\u00a0 Unrelenting,\u00a0 PCC\u00a0 members\u00a0 caught\u00a0 Ramos\u2010\nBraga\u00a0at\u00a0school\u00a0and\u00a0around\u00a0town,\u00a0physically\u00a0attacked\u00a0him\u00a0at\u00a0\nleast\u00a0ten\u00a0times,\u00a0and\u00a0eventually\u00a0threatened\u00a0him\u00a0with\u00a0death.\u00a0In\u2010\nitially,\u00a0 Ramos\u2010Braga\u00a0 reported\u00a0 these\u00a0 attacks\u00a0 to\u00a0 Brazilian\u00a0 o\ufb03\u2010\ncials,\u00a0but\u00a0local\u00a0police\u00a0did\u00a0nothing\u00a0in\u00a0response\u00a0and\u00a0eventually,\u00a0\no\ufb03cers\u00a0would\u00a0beat\u00a0him\u00a0when\u00a0he\u00a0made\u00a0reports,\u00a0claiming\u00a0that\u00a0\nhe\u00a0 was\u00a0a\u00a0suspected\u00a0gang\u00a0 member.\u00a0At\u00a0 age\u00a016\u00a0 he\u00a0stopped\u00a0re\u2010\nporting\u00a0his\u00a0PCC\u00a0encounters\u00a0to\u00a0police\u00a0because\u00a0in\u00a0one\u00a0instance\u00a0\no\ufb03cers\u00a0beat\u00a0him\u00a0until\u00a0he\u00a0spat\u00a0blood,\u00a0and\u00a0he\u00a0came\u00a0to\u00a0believe\u00a0\nthat\u00a0the\u00a0police\u00a0were\u00a0paid\u00a0by\u00a0the\u00a0PCC\u00a0to\u00a0harm\u00a0him.\u00a0When\u00a0Ra\u2010\nmos\u2010Braga\u00a0was\u00a0about\u00a018\u00a0years\u00a0old,\u00a0PCC\u00a0members\u00a0o\ufb00ered\u00a0him\u00a0\none\u00a0\u201clast\u00a0chance\u201d\u00a0to\u00a0join;\u00a0after\u00a0he\u00a0refused\u00a0they\u00a0assaulted\u00a0him\u00a0\nwith\u00a0pipes\u2014severely\u00a0injuring\u00a0him\u00a0and\u00a0hospitalizing\u00a0him\u00a0for\u00a0\ntwo\u00a0weeks.\u00a0He\u00a0stopped\u00a0attending\u00a0college\u00a0and\u00a0spent\u00a0months\u00a0\nmoving\u00a0between\u00a0homes\u00a0of\u00a0his\u00a0family\u00a0members\u00a0in\u00a0other\u00a0parts\u00a0\nof\u00a0the\u00a0city\u00a0and\u00a0another\u00a0town.\u00a0When\u00a0he\u00a0returned\u00a0to\u00a0S\u00e3o\u00a0Paulo,\u00a0\n\fNo.\u00a017\u20101998\u00a0                                                          3\u00a0\n\na\u00a0PCC\u00a0member\u00a0shot\u00a0him\u00a0from\u00a0behind,\u00a0putting\u00a0him\u00a0back\u00a0in\u00a0the\u00a0\nhospital\u00a0for\u00a0days.\u00a0\u00a0\n    In\u00a0 January\u00a0 1999,\u00a0 three\u00a0 months\u00a0 after\u00a0 being\u00a0 shot,\u00a0 Ramos\u2010\nBraga\u00a0was\u00a0admitted\u00a0to\u00a0the\u00a0United\u00a0States\u00a0on\u00a0a\u00a0student\u00a0visa.\u00a0He\u00a0\neventually\u00a0married\u00a0a\u00a0U.S.\u00a0citizen,\u00a0but\u00a0the\u00a0two\u00a0had\u00a0a\u00a0tumultu\u2010\nous\u00a0relationship.\u00a0Ramos\u2010Braga\u00a0estimated\u00a0that\u00a0his\u00a0wife\u00a0physi\u2010\ncally\u00a0abused\u00a0him\u00a0over\u00a0100\u00a0times.\u00a0\u00a0\n   Seven\u00a0years\u00a0after\u00a0he\u00a0arrived,\u00a0the\u00a0Department\u00a0of\u00a0Homeland\u00a0\nSecurity\u00a0 issued\u00a0 a\u00a0 Notice\u00a0 to\u00a0 Appear\u00a0 charging\u00a0 Ramos\u2010Braga\u00a0\nwith\u00a0overstaying\u00a0his\u00a0visa\u00a0and\u00a0therefore\u00a0being\u00a0removable\u00a0un\u2010\nder\u00a0 8\u00a0U.S.C.\u00a0 \u00a7\u00a01227(a)(1)(B).\u00a0 Ramos\u2010Braga\u00a0 conceded\u00a0 his\u00a0 re\u2010\nmovability\u00a0and\u00a0eventually\u00a0sought\u00a0special\u2010rule\u00a0cancellation\u00a0of\u00a0\nremoval\u00a0for\u00a0battered\u00a0spouses\u00a0and\u00a0withholding\u00a0of\u00a0removal\u00a0un\u2010\nder\u00a08\u00a0U.S.C.\u00a0\u00a7\u00a01231(b)(3)\u00a0and\u00a0CAT.\u00a0\u00a0\n    While\u00a0 removal\u00a0 proceedings\u00a0 were\u00a0 pending,\u00a0 Ramos\u2010Braga\u00a0\nand\u00a0his\u00a0wife\u00a0got\u00a0into\u00a0a\u00a0fight.\u00a0He\u00a0was\u00a0convicted\u00a0of\u00a0battery\u00a0un\u2010\nder\u00a0Wisconsin\u00a0law\u00a0and,\u00a0after\u00a0he\u00a0used\u00a0a\u00a0jailhouse\u00a0phone\u00a0to\u00a0ask\u00a0\nhis\u00a0 wife\u00a0 not\u00a0 to\u00a0 testify,\u00a0 intimidation\u00a0 of\u00a0 a\u00a0 witness,\u00a0 WIS.\u00a0 STAT.\u00a0\n\u00a7\u00a7\u00a0940.19(1),\u00a0940.42.\u00a0DHS\u00a0added\u00a0a\u00a0charge\u00a0that\u00a0he\u00a0was\u00a0remov\u2010\nable\u00a0 under\u00a0 8\u00a0 U.S.C.\u00a0 \u00a7\u00a0 1227(a)(2)(A)(ii)\u00a0 for\u00a0 having\u00a0 been\u00a0 con\u2010\nvicted\u00a0 of\u00a0 two\u00a0 crimes\u00a0 involving\u00a0 moral\u00a0 turpitude.\u00a0 He\u00a0 chal\u2010\nlenged\u00a0removability\u00a0on\u00a0this\u00a0ground.\u00a0\u00a0\n    At\u00a0 his\u00a0 removal\u00a0 hearing,\u00a0 Ramos\u2010Braga\u00a0 testified\u00a0 about\u00a0 the\u00a0\nbeatings\u00a0 by\u00a0 PCC\u00a0 members\u00a0 and\u00a0 police\u00a0 o\ufb03cers.\u00a0 He\u00a0 also\u00a0 said\u00a0\nthat\u00a0 the\u00a0 gang\u00a0 recruited\u00a0 young\u00a0 men\u00a0 and\u00a0 that\u00a0 he\u00a0 believed\u00a0 he\u00a0\nspecifically\u00a0was\u00a0recruited\u00a0because\u00a0of\u00a0something\u00a0his\u00a0father\u00a0had\u00a0\ndone,\u00a0but\u00a0he\u00a0did\u00a0not\u00a0know\u00a0what.\u00a0The\u00a0IJ\u00a0found\u00a0Ramos\u2010Braga\u00a0\ncredible\u00a0but\u00a0denied\u00a0his\u00a0applications\u00a0for\u00a0special\u2010rule\u00a0cancella\u2010\ntion\u00a0and\u00a0withholding\u00a0and\u00a0ordered\u00a0him\u00a0removed\u00a0to\u00a0Brazil.\u00a0\u00a0\n\f4\u00a0                                                       No.\u00a017\u20101998\u00a0\n\n     To\u00a0 obtain\u00a0 special\u2010rule\u00a0 cancellation,\u00a0 Ramos\u2010Braga\u00a0 had\u00a0 to\u00a0\nprove,\u00a0among\u00a0other\u00a0things,\u00a0that\u00a0he\u00a0had\u00a0been\u00a0battered\u00a0by\u00a0his\u00a0\nwife\u00a0and\u00a0was\u00a0not\u00a0subject\u00a0to\u00a0certain\u00a0disqualifying\u00a0grounds\u00a0of\u00a0\nremovability\u00a0or\u00a0inadmissibility.\u00a0See\u00a08\u00a0U.S.C.\u00a0\u00a7\u00a01229b(b)(2).\u00a0The\u00a0\nIJ\u00a0 concluded\u00a0 that\u00a0 Ramos\u2010Braga\u00a0 was\u00a0 disqualified\u00a0 on\u00a0 two\u00a0\ngrounds:\u00a0his\u00a0convictions\u00a0for\u00a0battery\u00a0and\u00a0witness\u00a0intimidation\u00a0\nwere\u00a0crimes\u00a0of\u00a0moral\u00a0turpitude,\u00a0and\u00a0he\u00a0had\u00a0been\u00a0confined\u00a0in\u00a0\nexcess\u00a0 of\u00a0 five\u00a0 years\u00a0 total\u00a0 for\u00a0 past\u00a0 convictions.\u00a0 See\u00a0 8\u00a0 U.S.C.\u00a0\n\u00a7\u00a7\u00a01229b(b)(2)(A)(iv),\u00a0       1182(a)(2)(A)(i)(I),\u00a0    1182(a)(2)(B),\u00a0\n1227(a)(2)(A)(ii).\u00a0\u00a0\n    Ramos\u2010Braga\u00a0could\u00a0receive\u00a0withholding\u00a0of\u00a0removal\u00a0in\u00a0two\u00a0\nways:\u00a0either\u00a0under\u00a0statute\u00a0or\u00a0under\u00a0CAT.\u00a0To\u00a0receive\u00a0withhold\u2010\ning\u00a0of\u00a0removal\u00a0under\u00a0statute,\u00a0he\u00a0had\u00a0to\u00a0prove\u00a0that\u00a0it\u00a0was\u00a0more\u00a0\nlikely\u00a0than\u00a0not\u00a0that,\u00a0if\u00a0he\u00a0were\u00a0removed,\u00a0he\u00a0would\u00a0be\u00a0perse\u2010\ncuted\u00a0in\u00a0Brazil\u00a0on\u00a0account\u00a0of\u00a0his\u00a0membership\u00a0in\u00a0a\u00a0particular\u00a0\nsocial\u00a0group.\u00a0See\u00a0id.\u00a0\u00a7\u00a01231(b)(3);\u00a08\u00a0C.F.R.\u00a0\u00a7\u00a01208.16(b).\u00a0The\u00a0IJ\u00a0\nconcluded\u00a0 that\u00a0 Ramos\u2010Braga\u00a0 su\ufb00ered\u00a0 past\u00a0 persecution\u00a0 but\u00a0\npresented\u00a0\u201clittle\u00a0proof\u201d\u00a0that\u00a0this\u00a0persecution\u00a0was\u00a0on\u00a0account\u00a0\nof\u00a0his\u00a0particular\u00a0social\u00a0group,\u00a0namely\u00a0his\u00a0family\u00a0ties\u00a0to\u00a0his\u00a0fa\u2010\nther.\u00a0Instead,\u00a0\u201cthe\u00a0greater\u00a0weight\u00a0of\u00a0the\u00a0evidence\u00a0support[ed]\u00a0\nthe\u00a0conclusion\u00a0that\u00a0he\u00a0was\u00a0persecuted\u00a0because\u00a0he\u00a0refused\u00a0the\u00a0\nPCC\u2019s\u00a0recruitment\u00a0e\ufb00orts.\u201d\u00a0To\u00a0merit\u00a0withholding\u00a0under\u00a0CAT,\u00a0\nRamos\u2010Braga\u00a0had\u00a0to\u00a0demonstrate\u00a0that\u00a0it\u00a0was\u00a0more\u00a0likely\u00a0than\u00a0\nnot\u00a0that,\u00a0if\u00a0removed\u00a0to\u00a0Brazil,\u00a0he\u00a0would\u00a0be\u00a0tortured\u00a0by\u00a0or\u00a0with\u00a0\nthe\u00a0 acquiescence\u00a0 of\u00a0 a\u00a0 public\u00a0 o\ufb03cial.\u00a0 See\u00a0 8\u00a0 C.F.R.\u00a0\n\u00a7\u00a01208.16(c)(2).\u00a0 The\u00a0 IJ\u00a0 determined\u00a0 that\u00a0 he\u00a0 did\u00a0 not\u00a0 carry\u00a0 his\u00a0\nburden\u00a0to\u00a0prove\u00a0that\u00a0he\u00a0was\u00a0more\u00a0likely\u00a0than\u00a0not\u00a0to\u00a0be\u00a0tor\u2010\ntured\u00a0by\u00a0either\u00a0the\u00a0police\u00a0or\u00a0PCC.\u00a0\u00a0\n\fNo.\u00a017\u20101998\u00a0                                                       5\u00a0\n\n   Ramos\u2010Braga,\u00a0who\u00a0was\u00a0represented\u00a0by\u00a0counsel,\u00a0appealed\u00a0\nthe\u00a0denial\u00a0of\u00a0his\u00a0applications\u00a0for\u00a0withholding\u00a0but\u00a0not\u00a0the\u00a0de\u2010\nnial\u00a0 of\u00a0 special\u2010rule\u00a0 cancellation.\u00a0 The\u00a0 Board\u00a0 a\ufb03rmed\u00a0 the\u00a0 IJ\u2019s\u00a0\ndecision\u00a0on\u00a0December\u00a018,\u00a02014.\u00a0\u00a0\n    In\u00a0January\u00a02015,\u00a0Ramos\u2010Braga\u00a0petitioned\u00a0this\u00a0court\u00a0for\u00a0re\u2010\nview\u00a0and\u00a0moved\u00a0to\u00a0stay\u00a0his\u00a0removal.\u00a0His\u00a0attorney\u00a0ended\u00a0the\u00a0\nrepresentation\u00a0over\u00a0a\u00a0fee\u00a0dispute,\u00a0however,\u00a0and\u00a0Ramos\u2010Braga\u00a0\ncontinued\u00a0pro\u00a0se,\u00a0filing\u00a0motions\u00a0in\u00a0this\u00a0court\u00a0and,\u00a0after\u00a0his\u00a0pe\u2010\ntition\u00a0 was\u00a0 denied,\u00a0 another\u00a0 petition\u00a0 for\u00a0 review\u00a0 that\u00a0 was\u00a0 dis\u2010\nmissed\u00a0for\u00a0lack\u00a0of\u00a0jurisdiction\u00a0for\u00a0having\u00a0been\u00a0filed\u00a0more\u00a0than\u00a0\n30\u00a0days\u00a0after\u00a0the\u00a0final\u00a0order\u00a0of\u00a0removal.\u00a0\u00a0\n    Ramos\u2010Braga,\u00a0still\u00a0pro\u00a0se,\u00a0moved\u00a0the\u00a0Board\u00a0to\u00a0reopen\u00a0pro\u2010\nceedings\u00a0on\u00a0his\u00a0applications\u00a0for\u00a0relief\u00a0from\u00a0removal\u00a0and\u00a0to\u00a0re\u2010\nconsider\u00a0its\u00a0dismissal\u00a0order.\u00a0The\u00a0Board\u00a0denied\u00a0his\u00a0motion\u00a0as\u00a0\nuntimely\u00a0in\u00a0June\u00a02015,\u00a0but\u00a0he\u00a0maintains\u00a0he\u00a0never\u00a0received\u00a0no\u2010\ntice\u00a0of\u00a0this\u00a0decision.\u00a0\u00a0\n    Ramos\u2010Braga\u00a0filed\u00a0a\u00a0second\u00a0pro\u00a0se\u00a0motion\u00a0to\u00a0reopen\u00a0or\u00a0re\u2010\nconsider\u00a0on\u00a0August\u00a031,\u00a02015,\u00a0and\u00a0at\u00a0issue\u00a0here\u00a0is\u00a0the\u00a0Board\u2019s\u00a0\ndenial\u00a0of\u00a0that\u00a0motion\u00a0on\u00a0the\u00a0grounds\u00a0that\u00a0it\u00a0was\u00a0untimely\u00a0and\u00a0\nsuccessive.\u00a0Ramos\u2010Braga\u00a0explained\u00a0that\u00a0his\u00a0motion\u00a0to\u00a0reopen\u00a0\nwas\u00a0late\u00a0because\u00a0his\u00a0former\u00a0attorney\u00a0had\u00a0promised\u00a0repeatedly\u00a0\nto\u00a0file\u00a0a\u00a0timely\u00a0motion,\u00a0but\u00a0he\u00a0never\u00a0did.\u00a0He\u00a0also\u00a0said\u00a0that\u00a0con\u2010\nditions\u00a0in\u00a0Brazil\u00a0had\u00a0gotten\u00a0worse\u00a0since\u00a0the\u00a0hearing,\u00a0and\u00a0he\u00a0\no\ufb00ered\u00a0 evidence\u00a0to\u00a0 that\u00a0e\ufb00ect.\u00a0A\u00a0year\u00a0later,\u00a0in\u00a0August\u00a02016,\u00a0\nRamos\u2010Braga\u00a0retained\u00a0his\u00a0present\u00a0attorney,\u00a0who\u00a0filed\u00a0a\u00a0sup\u2010\nplemental\u00a0brief\u00a0supporting\u00a0the\u00a0still\u2010pending\u00a0second\u00a0motion\u00a0to\u00a0\nreopen.\u00a0Through\u00a0counsel,\u00a0Ramos\u2010Braga\u00a0argued\u00a0that\u00a0his\u00a0sec\u2010\nond\u00a0motion\u00a0to\u00a0reopen\u00a0should\u00a0not\u00a0have\u00a0been\u00a0barred\u00a0because\u00a0\nthe\u00a0 exceptions\u00a0for\u00a0equitable\u00a0tolling\u00a0for\u00a0ine\ufb00ective\u00a0assistance\u00a0\nof\u00a0counsel\u00a0and\u00a0changed\u00a0conditions\u00a0in\u00a0the\u00a0country\u00a0of\u00a0removal\u00a0\n\f6\u00a0                                                       No.\u00a017\u20101998\u00a0\n\nexcused\u00a0his\u00a0noncompliance.\u00a0Regarding\u00a0the\u00a0first\u00a0exception,\u00a0Ra\u2010\nmos\u2010Braga\u00a0said\u00a0that\u00a0his\u00a0attorney\u00a0in\u00a0the\u00a0original\u00a0appeal\u00a0to\u00a0the\u00a0\nBoard\u00a0 had\u00a0 waived\u00a0 meritorious\u00a0 arguments\u00a0 for\u00a0 special\u2010rule\u00a0\ncancellation\u00a0and\u00a0withholding\u00a0under\u00a0CAT.\u00a0\u00a0\n     The\u00a0Board\u00a0denied\u00a0the\u00a0second\u00a0motion\u00a0to\u00a0reopen\u00a0based\u00a0on\u00a0\nits\u00a0 conclusion\u00a0 that\u00a0 Ramos\u2010Braga\u00a0 did\u00a0 not\u00a0 meet\u00a0 either\u00a0 excep\u2010\ntion.\u00a0Equitable\u00a0tolling\u00a0could\u00a0not\u00a0benefit\u00a0him,\u00a0the\u00a0Board\u00a0said,\u00a0\nbecause\u00a0 he\u00a0 did\u00a0 not\u00a0 file\u00a0 his\u00a0 motion\u00a0 as\u00a0 soon\u00a0 as\u00a0 possible\u00a0 after\u00a0\nlearning\u00a0 of\u00a0 his\u00a0 former\u00a0 attorney\u2019s\u00a0 alleged\u00a0 errors,\u00a0 nor\u00a0 was\u00a0 he\u00a0\nprejudiced\u00a0by\u00a0any\u00a0possible\u00a0error.\u00a0The\u00a0Board\u00a0also\u00a0concluded\u00a0\nthat\u00a0he\u00a0did\u00a0not\u00a0o\ufb00er\u00a0evidence\u00a0of\u00a0conditions\u00a0in\u00a0Brazil\u00a0that\u00a0had\u00a0\nchanged\u00a0since\u00a0the\u00a0removal\u00a0hearing;\u00a0his\u00a0evidence\u00a0of\u00a0\u201congoing\u201d\u00a0\nPCC\u00a0threats\u00a0were\u00a0a\u00a0\u201ccontinuation\u201d\u00a0of\u00a0past\u00a0harms\u00a0he\u00a0experi\u2010\nenced\u00a0in\u00a0Brazil.\u00a0\u00a0\n                                  II.\u00a0\n    Noncitizens\u00a0 can\u00a0 file\u00a0 just\u00a0 one\u00a0 motion\u00a0 to\u00a0 reopen\u00a0 immigra\u2010\ntion\u00a0proceedings,\u00a0and\u00a0that\u00a0motion\u00a0must\u00a0be\u00a0submitted\u00a0within\u00a0\n90\u00a0 days\u00a0 of\u00a0 the\u00a0 final\u00a0 order\u00a0 of\u00a0 removal.\u00a0 See\u00a08\u00a0U.S.C.\u00a0\n\u00a7\u00a01229a(c)(7)(A),\u00a0(C)(i).\u00a0These\u00a0time\u00a0and\u00a0numerical\u00a0limits\u00a0are,\u00a0\nhowever,\u00a0non\u2010jurisdictional\u00a0claim\u2010processing\u00a0rules,\u00a0subject\u00a0to\u00a0\nthe\u00a0 doctrine\u00a0 of\u00a0 equitable\u00a0 tolling\u00a0 and\u00a0 statutory\u00a0 exceptions.\u00a0\nSee\u00a0Mata\u00a0v.\u00a0Lynch,\u00a0135\u00a0S.\u00a0Ct.\u00a02150,\u00a02154\u00a0(2015);\u00a0Ji\u00a0Cheng\u00a0Ni\u00a0v.\u00a0\nHolder,\u00a0 715\u00a0 F.3d\u00a0 620,\u00a0 623\u00a0 (7th\u00a0 Cir.\u00a0 2013)\u00a0 (citing\u00a0 8\u00a0U.S.C.\u00a0\n\u00a7\u00a01229a(c)(7)(C)(ii));\u00a0 Pervaiz\u00a0 v.\u00a0 Gonzales,\u00a0 405\u00a0 F.3d\u00a0 488,\u00a0 490\u00a0\n(7th\u00a0Cir.\u00a02005).\u00a0\u00a0\n   The\u00a0question\u00a0here\u00a0is\u00a0narrow:\u00a0we\u00a0must\u00a0decide\u00a0only\u00a0whether\u00a0\nthe\u00a0 Board\u00a0 wrongly\u00a0 concluded\u00a0 that\u00a0 neither\u00a0 equitable\u00a0 tolling\u00a0\nnor\u00a0 changed\u00a0 conditions\u00a0 excuse\u00a0 the\u00a0 limits\u00a0 on\u00a0 Ramos\u2010Braga\u2019s\u00a0\n\fNo.\u00a017\u20101998\u00a0                                                                       7\u00a0\n\nsecond\u00a0motion\u00a0to\u00a0reopen.1\u00a0This\u00a0court\u00a0reviews\u00a0the\u00a0Board\u2019s\u00a0de\u2010\nnial\u00a0of\u00a0a\u00a0motion\u00a0to\u00a0reopen\u00a0for\u00a0an\u00a0abuse\u00a0of\u00a0discretion,\u00a0and\u00a0an\u00a0\nabuse\u00a0occurs\u00a0if\u00a0the\u00a0decision\u00a0lacks\u00a0a\u00a0\u201crational\u00a0explanation,\u00a0in\u2010\nexplicably\u00a0depart[s]\u00a0from\u00a0established\u00a0policies,\u00a0or\u00a0rest[s]\u00a0on\u00a0[ei\u2010\nther]\u00a0an\u00a0impermissible\u00a0basis,\u201d\u00a0Marinov\u00a0v.\u00a0Holder,\u00a0687\u00a0F.3d\u00a0365,\u00a0\n368\u00a0(7th\u00a0Cir.\u00a02012),\u00a0or\u00a0legal\u00a0error,\u00a0Habib\u00a0v.\u00a0Lynch,\u00a0787\u00a0F.3d\u00a0826,\u00a0\n831\u00a0(7th\u00a0Cir.\u00a02015).\u00a0\u00a0\n     A. Equitable\u00a0Tolling\u00a0\n   Ramos\u2010Braga\u00a0contends\u00a0that\u00a0the\u00a0Board\u00a0wrongly\u00a0refused\u00a0to\u00a0\nequitably\u00a0 toll\u00a0 the\u00a0 limits\u00a0 on\u00a0 his\u00a0 second\u00a0 motion\u00a0 to\u00a0 reopen\u00a0 his\u00a0\napplications\u00a0for\u00a0special\u2010rule\u00a0cancellation\u00a0and\u00a0withholding\u00a0of\u00a0\nremoval\u00a0under\u00a0CAT.\u00a0Equitable\u00a0tolling\u00a0applies\u00a0if\u00a0the\u00a0noncitizen\u00a0\ndemonstrates\u00a0prejudice\u00a0from\u00a0counsel\u2019s\u00a0deficient\u00a0performance\u00a0\nand\u00a0exhibits\u00a0diligence\u00a0by\u00a0seeking\u00a0relief\u00a0as\u00a0soon\u00a0as\u00a0reasonably\u00a0\npossible.\u00a0See\u00a0Yusev\u00a0v.\u00a0Sessions,\u00a0851\u00a0F.3d\u00a0763,\u00a0767\u00a0(7th\u00a0Cir.\u00a02017).\u00a0\u00a0\n    Even\u00a0if\u00a0we\u00a0assume\u00a0the\u00a0Board\u00a0erred\u00a0in\u00a0its\u00a0analysis\u00a0of\u00a0dili\u2010\ngence,\u00a0Ramos\u2010Braga\u00a0has\u00a0failed\u00a0to\u00a0show\u00a0that\u00a0he\u00a0was\u00a0prejudiced\u00a0\nby\u00a0his\u00a0former\u00a0attorney\u2019s\u00a0errors.\u00a0Ramos\u2010Braga\u00a0argues\u00a0that\u00a0he\u00a0\nwas\u00a0prejudiced\u00a0by\u00a0the\u00a0attorney\u2019s\u00a0failures\u00a0to\u00a0appeal\u00a0(1)\u00a0the\u00a0de\u2010\nnial\u00a0of\u00a0his\u00a0application\u00a0for\u00a0special\u2010rule\u00a0cancellation\u00a0and\u00a0(2)\u00a0the\u00a0\nIJ\u2019s\u00a0conclusion,\u00a0in\u00a0denying\u00a0CAT\u00a0relief,\u00a0that\u00a0the\u00a0PCC\u00a0was\u00a0not\u00a0\nlikely\u00a0 to\u00a0 torture\u00a0 him\u00a0 with\u00a0 the\u00a0 government\u2019s\u00a0 acquiescence\u00a0\nupon\u00a0his\u00a0return\u00a0to\u00a0Brazil.\u00a0\n\n\u00a0\u00a0\u00a0\u00a0\u00a0\u00a0\u00a0\u00a0\u00a0\u00a0\u00a0\u00a0\u00a0\u00a0\u00a0\u00a0\u00a0\u00a0\u00a0\u00a0\u00a0\u00a0\u00a0\u00a0\u00a0\u00a0\u00a0\u00a0\u00a0\u00a0\u00a0\u00a0\u00a0\u00a0\u00a0\u00a0\u00a0\u00a0\u00a0\u00a0\u00a0\u00a0\u00a0\u00a0\u00a0\u00a0\u00a0\u00a0\u00a0\n1\u00a0Ramos\u2010Braga\u00a0also\u00a0argues\u00a0that\u00a0the\u00a0Board\u00a0wrongly\u00a0denied\u00a0his\u00a0motion\u00a0to\u00a0\n\nreconsider\u00a0the\u00a0Board\u2019s\u00a0order\u00a0dismissing\u00a0his\u00a0original\u00a0appeal.\u00a0The\u00a0Board\u00a0de\u2010\nnied\u00a0 this\u00a0 motion\u00a0 also\u00a0 for\u00a0 being\u00a0 inexcusably\u00a0 untimely\u00a0 and\u00a0 numerically\u00a0\nbarred,\u00a0 see\u00a0 8\u00a0U.S.C.\u00a0 \u00a7\u00a01229a(c)(6)(A),\u00a0 (B);\u00a0 8\u00a0 C.F.R.\u00a0 \u00a7\u00a0 1003.2(b)(2),\u00a0 without\u00a0\nconsidering\u00a0whether\u00a0the\u00a0underlying\u00a0dismissal\u00a0order\u00a0required\u00a0reconsider\u2010\nation.\u00a0We\u00a0therefore\u00a0have\u00a0no\u00a0merits\u00a0decision\u00a0to\u00a0review\u00a0on\u00a0the\u00a0issue\u00a0of\u00a0re\u2010\nconsideration.\u00a0\u00a0\n\f8\u00a0                                                              No.\u00a017\u20101998\u00a0\n\n           1.\u00a0         Special\u2010Rule\u00a0Cancellation\u00a0\n    Ramos\u2010Braga\u00a0 contends\u00a0 that\u00a0 his\u00a0 former\u00a0 attorney\u00a0 should\u00a0\nhave\u00a0appealed\u00a0the\u00a0denial\u00a0of\u00a0special\u2010rule\u00a0cancellation\u00a0and\u00a0ar\u2010\ngued\u00a0that\u00a0he\u00a0remained\u00a0eligible\u00a0for\u00a0this\u00a0relief\u00a0because,\u00a0contrary\u00a0\nto\u00a0the\u00a0IJ\u2019s\u00a0conclusion,\u00a0his\u00a0Wisconsin\u00a0battery\u00a0conviction\u00a0is\u00a0not\u00a0\na\u00a0crime\u00a0involving\u00a0moral\u00a0turpitude.\u00a0\u00a0\n     But,\u00a0as\u00a0the\u00a0Board\u00a0determined\u00a0in\u00a0denying\u00a0the\u00a0motion\u00a0to\u00a0re\u2010\nopen,\u00a0this\u00a0battery\u00a0conviction\u00a0was\u00a0a\u00a0crime\u00a0involving\u00a0moral\u00a0tur\u2010\npitude\u00a0 under\u00a0 the\u00a0 law\u00a0 as\u00a0 it\u00a0 existed\u00a0 when\u00a0 Ramos\u2010Braga\u00a0 ap\u2010\npealed\u00a0 in\u00a0 December\u00a0 2014.\u00a0 Specifically,\u00a0 the\u00a0 Board\u00a0 concluded\u00a0\nthat\u00a0Ramos\u2010Braga\u2019s\u00a0battery\u00a0conviction\u00a0with\u00a0a\u00a0domestic\u2010abuse\u00a0\nenhancement,\u00a0 WIS.\u00a0 STAT.\u00a0 \u00a7\u00a7\u00a0940.19(1),\u00a0 973.055(1)(a),\u00a0 was\u00a0\nproperly\u00a0classified\u00a0by\u00a0the\u00a0IJ\u00a0as\u00a0a\u00a0crime\u00a0involving\u00a0moral\u00a0turpi\u2010\ntude\u00a0under\u00a0Matter\u00a0of\u00a0Silva\u2010Trevino,\u00a024\u00a0I.\u00a0&\u00a0N.\u00a0Dec.\u00a0687\u00a0(2008)\u00a0\n(Silva\u2010Trevino\u00a0I).\u00a0The\u00a0Board\u00a0observed\u00a0that\u00a0Silva\u2010Trevino\u00a0I\u00a0was\u00a0\nstill\u00a0 \u201ccontrolling\u201d\u00a0 when\u00a0 Ramos\u2010Braga\u2019s\u00a0 former\u00a0 attorney\u00a0 ap\u2010\npealed\u00a0 from\u00a0 the\u00a0 removal\u00a0 order,\u00a0 and\u00a0 thus\u00a0 Ramos\u2010Braga\u00a0 was\u00a0\nnot\u00a0prejudiced\u00a0by\u00a0the\u00a0failure\u00a0to\u00a0appeal\u00a0on\u00a0this\u00a0ground.2\u00a0\u00a0\n    Ramos\u00a0 Braga\u00a0 contends\u00a0 that\u00a0 his\u00a0 former\u00a0 attorney\u00a0 should\u00a0\nhave\u00a0 argued\u00a0 on\u00a0 appeal\u00a0 to\u00a0 the\u00a0 Board\u00a0 that\u00a0 the\u00a0 IJ\u00a0 misapplied\u00a0\nSilva\u2010Trevino\u00a0I.\u00a0But\u00a0the\u00a0IJ\u2019s\u00a0analysis\u00a0was\u00a0proper.\u00a0Silva\u00a0Trevino\u00a0I\u00a0\nestablished\u00a0a\u00a0three\u2010step\u00a0framework\u00a0for\u00a0determining\u00a0whether\u00a0\nan\u00a0 alien\u2019s\u00a0 conviction\u00a0 involved\u00a0 moral\u00a0 turpitude.\u00a0 First,\u00a0 the\u00a0 IJ\u00a0\nhad\u00a0to\u00a0decide\u00a0whether\u00a0there\u00a0was\u00a0a\u00a0\u201crealistic\u00a0probability\u201d\u00a0that\u00a0\nthe\u00a0criminal\u00a0statute\u00a0might\u00a0be\u00a0applied\u00a0to\u00a0punish\u00a0conduct\u00a0that\u00a0\n\n\u00a0\u00a0\u00a0\u00a0\u00a0\u00a0\u00a0\u00a0\u00a0\u00a0\u00a0\u00a0\u00a0\u00a0\u00a0\u00a0\u00a0\u00a0\u00a0\u00a0\u00a0\u00a0\u00a0\u00a0\u00a0\u00a0\u00a0\u00a0\u00a0\u00a0\u00a0\u00a0\u00a0\u00a0\u00a0\u00a0\u00a0\u00a0\u00a0\u00a0\u00a0\u00a0\u00a0\u00a0\u00a0\u00a0\u00a0\u00a0\u00a0\n2\u00a0Silva\u2010Trevino\u00a0I\u00a0was\u00a0vacated\u00a0by\u00a0the\u00a0Attorney\u00a0General,\u00a0Matter\u00a0of\u00a0Silva\u2010Tre\u2010\n\nvino,\u00a026\u00a0I.\u00a0&\u00a0N.\u00a0Dec.\u00a0550,\u00a0553\u00a0(2015)\u00a0(Silva\u2010Trevino\u00a0II),\u00a0and\u00a0the\u00a0Board\u00a0has\u00a0\nnow\u00a0 adopted\u00a0 the\u00a0 categorical\u00a0 approach\u00a0 as\u00a0 defined\u00a0 in\u00a0 Descamps\u00a0 v.\u00a0 United\u00a0\nStates,\u00a0570\u00a0U.S.\u00a0254\u00a0(2013),\u00a0see\u00a0Matter\u00a0of\u00a0Silva\u2010Trevino,\u00a026\u00a0I.\u00a0&\u00a0N.\u00a0Dec.\u00a0826,\u00a0\n830\u201331\u00a0(BIA\u00a02016)\u00a0(Silva\u2010Trevino\u00a0III).\u00a0\u00a0\n\fNo.\u00a017\u20101998\u00a0                                                         9\u00a0\n\ninvolves\u00a0 moral\u00a0 turpitude.\u00a0 If\u00a0 so,\u00a0 the\u00a0 IJ\u00a0 was\u00a0 next\u00a0 required\u00a0 to\u00a0\nlook\u00a0to\u00a0 the\u00a0record\u00a0of\u00a0 conviction\u2014the\u00a0 indictment,\u00a0 judgment,\u00a0\njury\u00a0instructions,\u00a0guilty\u00a0plea,\u00a0or\u00a0plea\u00a0transcript\u2014to\u00a0determine\u00a0\nif\u00a0 the\u00a0 conviction\u00a0 actually\u00a0 involved\u00a0 moral\u00a0 turpitude.\u00a0And\u00a0 fi\u2010\nnally,\u00a0if\u00a0the\u00a0record\u00a0of\u00a0conviction\u00a0did\u00a0not\u00a0answer\u00a0this\u00a0question,\u00a0\nthe\u00a0IJ\u00a0had\u00a0to\u00a0inquire\u00a0into\u00a0the\u00a0facts\u00a0of\u00a0the\u00a0prior\u00a0o\ufb00ense\u00a0by\u00a0look\u2010\ning\u00a0 to\u00a0 \u201cany\u00a0 evidence,\u00a0 otherwise\u00a0 admissible\u00a0 in\u00a0 removal\u00a0 pro\u2010\nceedings.\u201d\u00a0Silva\u2010Trevino\u00a0I,\u00a024\u00a0I.\u00a0&\u00a0N.\u00a0Dec.\u00a0at\u00a0698,\u00a0704;\u00a0Sanchez\u00a0\nv.\u00a0Holder,\u00a0757\u00a0F.3d\u00a0712,\u00a0717\u201318\u00a0(7th\u00a0Cir.\u00a02014).\u00a0The\u00a0IJ\u00a0here,\u00a0at\u00a0\nthe\u00a0last\u00a0step,\u00a0looked\u00a0to\u00a0a\u00a0police\u00a0statement\u00a0attached\u00a0to\u00a0the\u00a0crim\u2010\ninal\u00a0 complaint\u00a0 and\u00a0 determined\u00a0 that\u00a0 Ramos\u00a0 Braga\u00a0 had\u00a0 com\u2010\nmitted\u00a0 a\u00a0 crime\u00a0 involving\u00a0 moral\u00a0 turpitude\u00a0 because\u00a0 he\u00a0 inten\u2010\ntionally\u00a0caused\u00a0bodily\u00a0harm\u00a0to\u00a0his\u00a0wife.\u00a0See\u00a0Matter\u00a0of\u00a0Sanudo,\u00a0\n23\u00a0I.\u00a0&\u00a0N.\u00a0Dec.\u00a0968,\u00a0971\u201372\u00a0(BIA\u00a02006).\u00a0\n    Ramos\u2010Braga\u00a0asserts\u00a0that\u00a0the\u00a0IJ\u00a0should\u00a0not\u00a0have\u00a0proceeded\u00a0\npast\u00a0 step\u00a0 one,\u00a0 because\u00a0 the\u00a0 Wisconsin\u00a0 battery\u00a0 statute\u00a0 under\u00a0\nwhich\u00a0he\u00a0was\u00a0convicted\u00a0was\u00a0not\u00a0\u201cdivisible,\u201d\u00a0meaning\u00a0it\u00a0con\u2010\ntained\u00a0only\u00a0a\u00a0single\u00a0set\u00a0of\u00a0elements\u00a0to\u00a0prove.\u00a0See\u00a0Descamps\u00a0v.\u00a0\nUnited\u00a0States,\u00a0570\u00a0U.S.\u00a0254,\u00a0257\u00a0(2013).\u00a0But\u00a0Silva\u2010Trevino\u00a0I\u00a0did\u00a0\nnot\u00a0permit\u00a0the\u00a0IJ\u00a0to\u00a0end\u00a0the\u00a0inquiry\u00a0by\u00a0finding\u00a0the\u00a0statute\u00a0in\u2010\ndivisible;\u00a0instead,\u00a0it\u00a0required\u00a0the\u00a0IJ\u00a0to\u00a0proceed\u00a0to\u00a0step\u00a0two\u00a0if\u00a0\nthe\u00a0 statute\u00a0 \u201cencompasses\u00a0 both\u00a0 conduct\u00a0 that\u00a0 involves\u00a0 moral\u00a0\nturpitude\u00a0and\u00a0conduct\u00a0that\u00a0does\u00a0not.\u201d\u00a024\u00a0I.\u00a0&\u00a0N.\u00a0Dec.\u00a0at\u00a0698\u2013\n99.\u00a0 Ramos\u2010Braga\u00a0 does\u00a0 not\u00a0 contest\u00a0 the\u00a0 IJ\u2019s\u00a0 conclusion\u00a0 that\u00a0 a\u00a0\nWisconsin\u00a0battery\u00a0conviction\u00a0with\u00a0a\u00a0domestic\u2010abuse\u00a0enhance\u2010\nment\u00a0reaches\u00a0conduct\u00a0that\u00a0involves\u00a0moral\u00a0turpitude.\u00a0Hence,\u00a0\nSilva\u2010Trevino\u00a0I\u00a0required\u00a0the\u00a0IJ\u00a0to\u00a0proceed\u00a0past\u00a0step\u00a0one.\u00a0\u00a0\n   Still,\u00a0 Ramos\u2010Braga\u00a0 says\u00a0 that\u00a0 Descamps,\u00a0 a\u00a0 Supreme\u00a0 Court\u00a0\ncriminal\u00a0sentencing\u00a0case,\u00a0required\u00a0a\u00a0categorical\u00a0approach\u00a0that\u00a0\nprecluded\u00a0the\u00a0IJ\u00a0from\u00a0looking\u00a0past\u00a0an\u00a0indivisible\u00a0battery\u00a0stat\u2010\nute\u00a0 to\u00a0 decide\u00a0 whether\u00a0 his\u00a0 crime\u00a0 involved\u00a0 moral\u00a0 turpitude.\u00a0\n\f10\u00a0                                                    No.\u00a017\u20101998\u00a0\n\n570\u00a0U.S.\u00a0 at\u00a0 257\u201358.\u00a0 But\u00a0 Descamps\u00a0 did\u00a0 not\u00a0 overrule\u00a0 Silva\u2010Tre\u2010\nvino\u00a0I,\u00a0 which\u00a0 set\u00a0 forth\u00a0 in\u00a0 unequivocal\u00a0 terms\u00a0 the\u00a0 framework\u00a0\nthat\u00a0the\u00a0Attorney\u00a0General\u00a0required\u00a0IJs\u00a0to\u00a0follow\u00a0when\u00a0decid\u2010\ning\u00a0 if\u00a0 a\u00a0 conviction\u00a0 involved\u00a0 moral\u00a0 turpitude.\u00a0 Furthermore,\u00a0\nSilva\u2010Trevino\u00a0I\u00a0considered\u00a0the\u00a0categorical\u00a0approach\u00a0applied\u00a0in\u00a0\ncriminal\u00a0 cases\u00a0 like\u00a0 Descamps\u00a0 and\u00a0 did\u00a0 not\u00a0 find\u00a0 a\u00a0 compelling\u00a0\nneed\u00a0for\u00a0this\u00a0approach\u00a0in\u00a0the\u00a0immigration\u00a0context.\u00a0See\u00a0Silva\u2010\nTrevino\u00a0I,\u00a024\u00a0I.\u00a0&\u00a0N.\u00a0Dec.\u00a0at\u00a0700\u00a0(\u201c[T]he\u00a0rationale\u00a0for\u00a0the\u00a0lim\u2010\nits\u00a0\u2026\u00a0 on\u00a0 factual\u00a0 inquiries\u00a0 in\u00a0 criminal\u00a0 sentencing\u00a0 cases\u00a0 does\u00a0\nnot\u00a0carry\u00a0over\u00a0to\u00a0the\u00a0immigration\u00a0question\u201d\u00a0required\u00a0under\u00a0\nthe\u00a0immigration\u00a0statute.).\u00a0Unlike\u00a0the\u00a0categorical\u00a0approach\u00a0in\u00a0\nDescamps,\u00a0Silva\u2010Trevino\u00a0I\u00a0instructed\u00a0IJs\u00a0to\u00a0proceed\u00a0to\u00a0step\u00a0two:\u00a0\n\u201cIf\u00a0it\u00a0appears\u00a0that\u00a0the\u00a0government\u00a0in\u00a0question\u00a0would\u00a0apply\u00a0its\u00a0\ncriminal\u00a0 statute\u00a0 to\u00a0 reach\u00a0 both\u00a0 turpitudinous\u00a0 and\u00a0 non\u2010turpi\u2010\ntudinous\u00a0 acts\u2014perhaps\u00a0 because\u00a0 the\u00a0 statute\u00a0 is\u00a0 divisible,\u00a0 but\u00a0\nalso\u00a0because\u00a0the\u00a0statute\u00a0could\u00a0realistically\u00a0cover\u00a0a\u00a0wide\u00a0range\u00a0\nof\u00a0conduct.\u201d\u00a0Sanchez,\u00a0757\u00a0F.3d\u00a0at\u00a0717\u00a0(emphasis\u00a0supplied).\u00a0Alt\u2010\nhough\u00a0the\u00a0Attorney\u00a0General\u2019s\u00a0new\u00a0approach\u00a0to\u00a0determining\u00a0\na\u00a0 crime\u00a0 of\u00a0 moral\u00a0 turpitude\u00a0 adopts\u00a0 the\u00a0 categorical\u00a0 approach\u00a0\noutlined\u00a0by\u00a0Descamps,\u00a0the\u00a0IJ\u00a0was\u00a0not\u00a0permitted\u00a0to\u00a0ignore\u00a0the\u00a0\nAttorney\u00a0General\u2019s\u00a0then\u2010controlling\u00a0decision\u00a0by\u00a0anticipating\u00a0\nthis\u00a0change\u00a0in\u00a0the\u00a0law.\u00a0The\u00a0IJ\u00a0was\u00a0bound\u00a0by\u00a0Silva\u2010Trevino\u00a0I\u00a0and\u00a0\nthe\u00a0case\u00a0law\u00a0of\u00a0our\u00a0circuit.\u00a0Mata\u2010Guerrero\u00a0v.\u00a0Holder,\u00a0627\u00a0F.3d\u00a0\n256\u00a0(7th\u00a0Cir.\u00a02010);\u00a0Ali\u00a0v.\u00a0Mukasey,\u00a0521\u00a0F.3d\u00a0737\u00a0(7th\u00a0Cir.\u00a02008).\u00a0\u00a0\n    Ramos\u2010Braga\u00a0also\u00a0argues\u00a0that\u00a0the\u00a0IJ\u00a0erred\u00a0at\u00a0step\u00a0three\u00a0of\u00a0\nSilva\u2010Trevino\u00a0 I\u00a0 by\u00a0 ignoring\u00a0 evidence\u00a0 in\u00a0 the\u00a0 police\u00a0 statement\u00a0\nthat\u00a0he\u00a0was\u00a0the\u00a0victim,\u00a0not\u00a0the\u00a0aggressor.\u00a0But\u00a0the\u00a0IJ\u00a0noted\u00a0the\u00a0\npolice\u00a0 statement\u00a0 included\u00a0 Ramos\u2010Braga\u2019s\u00a0 story\u00a0 that\u00a0 he\u00a0 was\u00a0\nfleeing\u00a0from\u00a0his\u00a0wife\u00a0and\u00a0accidentally\u00a0struck\u00a0her\u00a0face\u00a0with\u00a0the\u00a0\ndoor.\u00a0Instead,\u00a0the\u00a0IJ\u00a0credited\u00a0the\u00a0wife\u2019s\u00a0version,\u00a0also\u00a0in\u00a0the\u00a0po\u2010\nlice\u00a0statement,\u00a0that\u00a0Ramos\u2010Braga\u00a0struck\u00a0her\u00a0face\u00a0with\u00a0his\u00a0hand\u00a0\n\fNo.\u00a017\u20101998\u00a0                                                      11\u00a0\n\nand\u00a0pushed\u00a0her\u00a0into\u00a0a\u00a0shelf,\u00a0causing\u00a0her\u00a0nose\u00a0and\u00a0lip\u00a0to\u00a0swell,\u00a0\nbruise,\u00a0and\u00a0bleed.\u00a0Thus,\u00a0the\u00a0IJ\u00a0did\u00a0not\u00a0ignore\u00a0evidence.\u00a0\u00a0\n     Because\u00a0 Silva\u2010Trevino\u00a0 I\u00a0 still\u00a0 applied\u00a0 when\u00a0 Ramos\u2010Braga\u00a0\nappealed\u00a0to\u00a0the\u00a0Board,\u00a0he\u00a0was\u00a0not\u00a0prejudiced\u00a0by\u00a0the\u00a0lack\u00a0of\u00a0a\u00a0\nchallenge\u00a0to\u00a0the\u00a0IJ\u2019s\u00a0classification\u00a0of\u00a0his\u00a0battery\u00a0conviction\u00a0in\u00a0\ndenying\u00a0 special\u2010rule\u00a0 cancellation.\u00a0 If\u00a0 his\u00a0 attorney\u00a0 had\u00a0 raised\u00a0\nthe\u00a0argument\u00a0he\u00a0presses\u00a0now,\u00a0the\u00a0Board\u00a0would\u00a0have\u00a0rejected\u00a0\nit,\u00a0as\u00a0it\u00a0reasonably\u00a0did\u00a0in\u00a0denying\u00a0the\u00a0motion\u00a0to\u00a0reopen.\u00a0\u00a0\n       2.\u00a0     Withholding\u00a0under\u00a0CAT\u00a0\n    Ramos\u2010Braga\u00a0argues\u00a0next\u00a0that\u00a0he\u00a0was\u00a0prejudiced\u00a0in\u00a0the\u00a0ap\u2010\npeal\u00a0of\u00a0his\u00a0denied\u00a0CAT\u00a0application.\u00a0He\u00a0contends\u00a0that\u00a0his\u00a0for\u2010\nmer\u00a0attorney\u00a0should\u00a0have\u00a0argued\u00a0that\u00a0the\u00a0IJ\u00a0failed\u00a0to\u00a0consider\u00a0\nevidence\u00a0that,\u00a0if\u00a0he\u00a0is\u00a0removed\u00a0to\u00a0Brazil,\u00a0the\u00a0PCC\u00a0would\u00a0tor\u2010\nture\u00a0him\u00a0without\u00a0intervention\u00a0by\u00a0public\u00a0o\ufb03cials.\u00a0In\u00a0denying\u00a0\nthe\u00a0second\u00a0motion\u00a0to\u00a0reopen,\u00a0the\u00a0Board\u00a0said\u00a0this\u00a0potential\u00a0er\u2010\nror\u00a0could\u00a0not\u00a0have\u00a0prejudiced\u00a0Ramos\u2010Braga\u00a0because\u00a0the\u00a0evi\u2010\ndence\u00a0he\u00a0o\ufb00ered,\u00a0to\u00a0the\u00a0IJ\u00a0originally\u00a0and\u00a0in\u00a0support\u00a0of\u00a0reopen\u2010\ning,\u00a0 could\u00a0 not\u00a0 establish\u00a0 that\u00a0 o\ufb03cial\u00a0 torture\u00a0 or\u00a0 acquiescence\u00a0\nwas\u00a0more\u00a0likely\u00a0than\u00a0not.\u00a0\u00a0\n\n    \u201cCAT\u00a0protection\u00a0requires\u00a0evidence\u00a0that\u00a0the\u00a0Petitioner\u00a0will\u00a0\nbe\u00a0tortured\u00a0by\u00a0the\u00a0government,\u00a0or\u00a0with\u00a0the\u00a0government\u2019s\u00a0ac\u2010\nquiescence.\u201d\u00a0Lopez\u00a0v.\u00a0Lynch,\u00a0810\u00a0F.3d\u00a0484,\u00a0492\u00a0(7th\u00a0Cir.\u00a02016).\u00a0\nAcquiescence\u00a0means\u00a0\u201cthe\u00a0public\u00a0o\ufb03cial,\u00a0prior\u00a0to\u00a0the\u00a0activity\u00a0\nconstituting\u00a0 torture,\u00a0 ha[d]\u00a0 awareness\u00a0 of\u00a0 such\u00a0 activity\u00a0 and\u00a0\nthereafter\u00a0 breach[ed]\u00a0his\u00a0 or\u00a0 her\u00a0 legal\u00a0 responsibility\u00a0 to\u00a0 inter\u2010\nvene\u00a0to\u00a0prevent\u00a0such\u00a0activity.\u201d\u00a08\u00a0C.F.R.\u00a0\u00a7\u00a01208.18(a)(7);\u00a0Lopez,\u00a0\n810\u00a0F.3d\u00a0at\u00a0493.\u00a0We\u00a0will\u00a0reverse\u00a0the\u00a0Board\u2019s\u00a0conclusion\u00a0that\u00a0\nRamos\u2010Braga\u2019s\u00a0 evidence\u00a0 is\u00a0 insu\ufb03cient\u00a0 only\u00a0 if\u00a0 the\u00a0 evidence\u00a0\ncompels\u00a0 the\u00a0 conclusion\u00a0 that\u00a0 o\ufb03cial\u00a0 acquiescence\u00a0 is\u00a0 more\u00a0\n\f12\u00a0                                                   No.\u00a017\u20101998\u00a0\n\nlikely\u00a0than\u00a0not.\u00a0See\u00a0Orellana\u2010Arias\u00a0v.\u00a0Sessions,\u00a0865\u00a0F.3d\u00a0476,\u00a0490\u00a0\n(7th\u00a0Cir.\u00a02017).\u00a0\u00a0\n\n    Relying\u00a0on\u00a0our\u00a0precedent\u00a0in\u00a0Rodriguez\u2010Molinero\u00a0v.\u00a0Lynch,\u00a0\n808\u00a0F.3d\u00a01134\u00a0(7th\u00a0Cir.\u00a02015),\u00a0Ramos\u2010Braga\u00a0argues\u00a0that\u00a0there\u00a0\nis\u00a0a\u00a0\u201csubstantial\u00a0risk\u201d\u00a0that\u00a0the\u00a0Brazilian\u00a0government\u00a0will\u00a0ac\u2010\nquiesce\u00a0to\u00a0his\u00a0torture\u00a0by\u00a0the\u00a0PCC\u00a0if\u00a0he\u00a0is\u00a0removed\u00a0to\u00a0Brazil.\u00a0\nBut\u00a0his\u00a0evidence\u00a0does\u00a0not\u00a0compel\u00a0that\u00a0conclusion.\u00a0\n\n    Ramos\u2010Braga\u00a0relies\u00a0heavily\u00a0on\u00a0the\u00a0violence\u00a0he\u00a0experienced\u00a0\nat\u00a0the\u00a0hands\u00a0of\u00a0the\u00a0police\u00a0and\u00a0the\u00a0PCC\u00a0when\u00a0he\u00a0was\u00a0a\u00a0teen\u2010\nager.\u00a0 Yet\u00a0 the\u00a0 fact\u00a0 that\u00a0 Ramos\u2010Braga\u00a0 was\u00a0 beaten\u00a0 by\u00a0 police\u00a0\nroughly\u00a0twenty\u00a0years\u00a0ago\u00a0does\u00a0not\u00a0show\u00a0that\u00a0he\u00a0is\u00a0likely\u00a0to\u00a0be\u00a0\ntortured\u00a0by\u00a0o\ufb03cials\u00a0today.\u00a0See\u00a0Lopez,\u00a0810\u00a0F.3d\u00a0at\u00a0493\u00a0(noting\u00a0\nthat\u00a0 man\u00a0 who\u00a0 stabbed\u00a0 petitioner\u00a0 twenty\u2010five\u00a0 years\u00a0 earlier\u00a0\nmay\u00a0 no\u00a0 longer\u00a0 seek\u00a0 to\u00a0 harm\u00a0 petitioner).\u00a0 Moreover,\u00a0 Ramos\u2010\nBraga\u00a0has\u00a0o\ufb00ered\u00a0nothing\u00a0more\u00a0than\u00a0his\u00a0own\u00a0speculation\u00a0that\u00a0\nthe\u00a0police\u00a0acted\u00a0at\u00a0the\u00a0PCC\u2019s\u00a0urging\u00a0when\u00a0they\u00a0attacked\u00a0him.\u00a0\nSee\u00a0Lhanzom\u00a0v.\u00a0Gonzales,\u00a0430\u00a0F.3d\u00a0833,\u00a0845\u00a0(7th\u00a0Cir.\u00a02005)\u00a0(re\u2010\nversing\u00a0IJ\u2019s\u00a0decision\u00a0that\u00a0rested\u00a0on\u00a0testimony\u00a0for\u00a0which\u00a0wit\u2010\nness\u00a0had\u00a0no\u00a0personal\u00a0knowledge).\u00a0The\u00a0evidence\u00a0of\u00a0his\u00a0beat\u2010\nings\u00a0by\u00a0the\u00a0PCC\u00a0in\u00a0the\u00a0late\u00a01990s\u00a0is\u00a0similarly\u00a0stale.\u00a0Even\u00a0if\u00a0the\u00a0\nBrazilian\u00a0government\u00a0acquiesced\u00a0to\u00a0that\u00a0violence,\u00a0its\u00a0conduct\u00a0\ntwenty\u00a0years\u00a0ago\u00a0is\u00a0not\u00a0compelling\u00a0evidence\u00a0of\u00a0how\u00a0the\u00a0gov\u2010\nernment\u00a0would\u00a0respond\u00a0to\u00a0such\u00a0violence\u00a0today.\u00a0\u00a0\n    Ramos\u2010Braga\u00a0 introduced\u00a0 more\u00a0 current\u00a0 evidence\u00a0 as\u00a0 well.\u00a0\nHis\u00a0 strongest\u00a0 evidence\u00a0 is\u00a0 an\u00a0 affidavit\u00a0 from\u00a0 his\u00a0 mother.\u00a0 In\u00a0\n2016,\u00a0his\u00a0mother\u00a0complained\u00a0to\u00a0police\u00a0after\u00a0PCC\u00a0members,\u00a0al\u2010\nlegedly\u00a0acting\u00a0on\u00a0a\u00a0vendetta\u00a0against\u00a0Ramos\u2010Braga,\u00a0robbed\u00a0his\u00a0\ngrandfather\u00a0 at\u00a0 home\u00a0 in\u00a0 2015\u00a0 and\u00a0 threatened\u00a0 his\u00a0 mother\u00a0 in\u00a0\n2016.\u00a0 According\u00a0 to\u00a0 Ramos\u2010Braga\u2019s\u00a0 mother,\u00a0 PCC\u00a0 members\u00a0\nstated\u00a0over\u00a0the\u00a0internet\u00a0that\u00a0they\u00a0\u201cwill\u00a0be\u00a0waiting\u201d\u00a0for\u00a0Ramos\u2010\n\fNo.\u00a017\u20101998\u00a0                                                     13\u00a0\n\nBraga\u00a0when\u00a0he\u00a0returns\u00a0home.\u00a0Officers\u00a0in\u00a0one\u00a0district\u00a0referred\u00a0\nhis\u00a0mother\u00a0to\u00a0another\u00a0district,\u00a0which\u00a0promised\u00a0to\u00a0investigate\u00a0\nthe\u00a02016\u00a0threats,\u00a0but\u00a0the\u00a0investigation\u00a0has\u00a0not\u00a0been\u00a0resolved.\u00a0\nRamos\u2010Braga\u00a0takes\u00a0the\u00a0referral\u00a0of\u00a0the\u00a0complaint\u00a0from\u00a0one\u00a0of\u2010\nfice\u00a0to\u00a0another\u00a0and\u00a0the\u00a0lack\u00a0of\u00a0resolution\u00a0as\u00a0evidence\u00a0that\u00a0the\u00a0\npolice\u00a0 are\u00a0 unwilling\u00a0 to\u00a0 protect\u00a0 his\u00a0 family\u2014and,\u00a0 ultimately,\u00a0\nhim\u2014from\u00a0the\u00a0PCC.\u00a0\n   The\u00a0PCC\u2019s\u00a0threats\u00a0to\u00a0Ramos\u2010Braga\u2019s\u00a0family\u00a0do\u00a0offer\u00a0sup\u2010\nport\u00a0for\u00a0his\u00a0contention\u00a0that\u00a0the\u00a0PCC\u00a0is\u00a0likely\u00a0to\u00a0torture\u00a0him\u00a0if\u00a0\nhe\u00a0returns\u00a0to\u00a0Brazil.\u00a0But\u00a0CAT\u00a0offers\u00a0protection\u00a0from\u00a0govern\u2010\nment\u00a0torture,\u00a0not\u00a0private\u00a0conduct.\u00a0Thus,\u00a0Ramos\u2010Braga\u00a0cannot\u00a0\nsecure\u00a0 relief\u00a0 simply\u00a0 by\u00a0 showing\u00a0 a\u00a0 substantial\u00a0 risk\u00a0 that\u00a0 the\u00a0\nPCC\u00a0will\u00a0torture\u00a0him;\u00a0he\u00a0must\u00a0demonstrate\u00a0that\u00a0there\u00a0is\u00a0a\u00a0sub\u2010\nstantial\u00a0 risk\u00a0that\u00a0Brazilian\u00a0 officials\u00a0will\u00a0acquiesce\u00a0in\u00a0the\u00a0tor\u2010\nture.\u00a0This\u00a0is\u00a0where\u00a0Ramos\u2010Braga\u2019s\u00a0claim\u00a0founders.\u00a0\u00a0\n    The\u00a0police\u00a0department\u2019s\u00a0response\u00a0to\u00a0the\u00a0complaint\u00a0lodged\u00a0\nby\u00a0Ramos\u2010Braga\u2019s\u00a0 mother\u00a0falls\u00a0far\u00a0 short\u00a0of\u00a0 establishing\u00a0that\u00a0\nthe\u00a0police\u00a0are\u00a0indifferent\u00a0to\u00a0or\u00a0complicit\u00a0in\u00a0the\u00a0PCC\u2019s\u00a0threats\u00a0\nto\u00a0Ramos\u2010Braga\u2019s\u00a0family.\u00a0For\u00a0one\u00a0thing,\u00a0the\u00a0police\u00a0promised\u00a0\nto\u00a0investigate\u2014they\u00a0neither\u00a0ignored\u00a0nor\u00a0denied\u00a0his\u00a0mother\u2019s\u00a0\nrequest\u00a0for\u00a0help.\u00a0Ramos\u2010Braga\u00a0contends\u00a0that\u00a0the\u00a0police\u00a0gave\u00a0\nhis\u00a0mother\u00a0the\u00a0run\u2010around,\u00a0but\u00a0the\u00a0evidence\u00a0does\u00a0not\u00a0support\u00a0\nthat\u00a0inference.\u00a0Referring\u00a0a\u00a0complaint\u00a0from\u00a0one\u00a0district\u00a0to\u00a0an\u2010\nother\u00a0 is\u00a0 more\u00a0 consistent\u00a0 with\u00a0 bureaucracy\u00a0 than\u00a0 animosity,\u00a0\nand\u00a0the\u00a0fact\u00a0that\u00a0the\u00a0investigation\u00a0is\u00a0not\u00a0yet\u00a0resolved\u00a0does\u00a0not\u00a0\nmean\u00a0that\u00a0the\u00a0police\u00a0are\u00a0turning\u00a0a\u00a0blind\u00a0eye\u00a0to\u00a0the\u00a0PCC.\u00a0\u00a0\n    Again,\u00a0we\u00a0will\u00a0only\u00a0disturb\u00a0the\u00a0Board\u2019s\u00a0determination\u00a0if\u00a0\nsubstantial\u00a0evidence\u00a0on\u00a0the\u00a0record\u00a0compels\u00a0a\u00a0contrary\u00a0conclu\u2010\nsion.\u00a0When\u00a0reviewing\u00a0a\u00a0claim\u00a0that\u00a0the\u00a0government\u00a0acquiesced\u00a0\nto\u00a0torture,\u00a0we\u00a0have\u00a0required\u00a0much\u00a0more\u00a0evidence\u00a0of\u00a0o\ufb03cial\u00a0\ncomplicity\u00a0or\u00a0corruption\u00a0to\u00a0satisfy\u00a0that\u00a0standard\u00a0than\u00a0Ramos\u2010\n\f14\u00a0                                                    No.\u00a017\u20101998\u00a0\n\nBraga\u00a0 has\u00a0 o\ufb00ered.\u00a0 For\u00a0 example,\u00a0 in\u00a0 Rodriguez\u2010Molinero,\u00a0 we\u00a0\ngranted\u00a0a\u00a0petition\u00a0for\u00a0review\u00a0because\u00a0the\u00a0petitioner\u00a0demon\u2010\nstrated\u00a0a\u00a0substantial\u00a0risk\u00a0that\u00a0the\u00a0Mexican\u00a0government\u00a0would\u00a0\nacquiesce\u00a0to,\u00a0or\u00a0even\u00a0collaborate\u00a0in,\u00a0his\u00a0torture\u00a0by\u00a0a\u00a0drug\u00a0car\u2010\ntel.\u00a0808\u00a0F.3d\u00a0at\u00a01138\u20131140.\u00a0This\u00a0conclusion\u00a0was\u00a0based\u00a0on\u00a0the\u00a0\nfact\u00a0 that\u00a0 the\u00a0 petitioner\u00a0 had\u00a0 been\u00a0 previously\u00a0 tortured\u00a0 by\u00a0 the\u00a0\npolice\u00a0at\u00a0the\u00a0behest\u00a0of\u00a0the\u00a0drug\u00a0cartel,\u00a0as\u00a0well\u00a0as\u00a0unchallenged\u00a0\nexpert\u00a0 testimony\u00a0 that\u00a0 the\u00a0 Mexican\u00a0 government\u00a0 is\u00a0 rife\u00a0 with\u00a0\ncorruption\u00a0and\u00a0helpless\u00a0to\u00a0prevent\u00a0gang\u00a0violence\u00a0throughout\u00a0\nthe\u00a0country.\u00a0Id.\u00a0at\u00a01136\u201337.\u00a0In\u00a0Wanjiru\u00a0v.\u00a0Holder,\u00a0705\u00a0F.3d\u00a0258\u00a0\n(7th\u00a0 Cir.\u00a0 2013),\u00a0 we\u00a0 remanded\u00a0 a\u00a0 CAT\u00a0 claim\u00a0 because\u00a0 the\u00a0 IJ\u00a0\nbrushed\u00a0 over\u00a0 \u201cextensive\u00a0 evidence\u201d\u00a0 that\u00a0 police\u00a0 and\u00a0govern\u2010\nment\u00a0o\ufb03cials\u00a0abetted\u00a0and\u00a0directed\u00a0a\u00a0gang\u00a0that\u00a0posed\u00a0a\u00a0threat\u00a0\nof\u00a0torture\u00a0to\u00a0the\u00a0petitioner.\u00a0Id.\u00a0at\u00a0266.\u00a0Indeed,\u00a0the\u00a0International\u00a0\nCriminal\u00a0 Court\u00a0 had\u00a0 \u201cconfirmed\u00a0 charges\u00a0 (a\u00a0 step\u00a0 similar\u00a0 to\u00a0\nfinding\u00a0probable\u00a0cause)\u201d\u00a0against\u00a0two\u00a0senior\u00a0Kenyan\u00a0o\ufb03cials\u00a0\nfor\u00a0allegedly\u00a0using\u00a0the\u00a0gang\u00a0to\u00a0murder\u00a0thousands\u00a0of\u00a0citizens.\u00a0\nId.\u00a0In\u00a0 Mendoza\u2010Sanchez,\u00a0808\u00a0F.3d\u00a0 1182\u00a0(7th\u00a0 Cir.\u00a02015),\u00a0 we\u00a0 re\u2010\nmanded\u00a0(at\u00a0the\u00a0government\u2019s\u00a0request)\u00a0and\u00a0said\u00a0that\u00a0an\u00a0appli\u2010\ncant\u00a0had\u00a0a\u00a0\u201cstrong\u201d\u00a0CAT\u00a0claim\u00a0because\u00a0he\u00a0had\u00a0evidence\u00a0that\u00a0\npolice\u00a0o\ufb03cers\u00a0in\u00a0Mexico\u00a0routinely\u00a0collaborated\u00a0with\u00a0and\u00a0pro\u2010\ntected\u00a0a\u00a0nationwide\u00a0gang\u00a0that\u00a0had\u00a0targeted\u00a0him.\u00a0Id.\u00a0at\u00a01184\u2013\n85.\u00a0A\u00a0human\u2010rights\u00a0report\u00a0from\u00a0the\u00a0State\u00a0Department\u00a0detailed\u00a0\nwidespread\u00a0 corruption\u00a0 of\u00a0 Mexican\u00a0 police,\u00a0 who,\u00a0 at\u00a0 both\u00a0 the\u00a0\ncity\u00a0and\u00a0state\u00a0level,\u00a0were\u00a0directly\u00a0involved\u00a0in\u00a0the\u00a0activities\u00a0of\u00a0\ndrug\u00a0organizations\u00a0by\u00a0\u201ckidnapping,\u00a0extort[ing],\u00a0and\u00a0provid\u2010\ning\u00a0protection\u00a0for,\u00a0or\u00a0acting\u00a0directly\u00a0on\u00a0behalf\u00a0of,\u00a0organized\u00a0\ncrime\u00a0and\u00a0drug\u00a0tra\ufb03ckers.\u201d\u00a0Id.\u00a0at\u00a01184.\u00a0\u00a0\n   In\u00a0each\u00a0of\u00a0these\u00a0cases,\u00a0the\u00a0petitioner\u00a0showed\u00a0that\u00a0the\u00a0gov\u2010\nernment\u00a0 is\u00a0 utterly\u00a0 indi\ufb00erent\u00a0 or\u00a0 downright\u00a0 complicit\u00a0 in\u00a0 the\u00a0\nface\u00a0 of\u00a0 violence\u00a0 and\u00a0 torture\u00a0 by\u00a0 gangs.\u00a0 Ramos\u2010Braga\u00a0 argues\u00a0\n\fNo.\u00a017\u20101998\u00a0                                                     15\u00a0\n\nthat\u00a0the\u00a0PCC\u00a0wields\u00a0similar\u00a0influence\u00a0in\u00a0the\u00a0Brazilian\u00a0govern\u2010\nment,\u00a0but\u00a0his\u00a0evidence\u00a0belies\u00a0that\u00a0argument.\u00a0\u00a0\n     Ramos\u2010Braga\u00a0contends\u00a0that\u00a0the\u00a0PCC\u00a0has\u00a0\u201cinfiltrated\u201d\u00a0the\u00a0\nBrazilian\u00a0police\u00a0forces,\u00a0and\u00a0he\u00a0o\ufb00ers\u00a0a\u00a0news\u00a0article\u00a0reporting\u00a0\nthat\u00a0 PCC\u00a0 members\u00a0 \u201cmay\u00a0 have\u00a0 participated\u201d\u00a0 in\u00a0 explosives\u00a0\ntrainings\u00a0for\u00a0police\u00a0o\ufb03cers\u00a0in\u00a0S\u00e3o\u00a0Paulo.\u00a0If\u00a0gang\u00a0members\u00a0had\u00a0\ninfiltrated\u00a0 police\u00a0 forces,\u00a0this\u00a0 would\u00a0indeed\u00a0be\u00a0evidence\u00a0that\u00a0\nthe\u00a0 government\u00a0 is\u00a0 unable\u00a0 to\u00a0 protect\u00a0 people\u00a0 targeted\u00a0 by\u00a0 the\u00a0\ngang.\u00a0See\u00a0Mendoza\u2010Sanchez,\u00a0808\u00a0F.3d\u00a0at\u00a01183,\u00a01185.\u00a0But\u00a0the\u00a0re\u2010\nport\u00a0Ramos\u2010Braga\u00a0o\ufb00ers\u00a0falls\u00a0well\u00a0short\u00a0of\u00a0showing\u00a0that\u00a0PCC\u00a0\nmembers\u00a0are\u00a0within\u00a0the\u00a0ranks\u00a0of\u00a0Brazilian\u00a0police.\u00a0According\u00a0\nto\u00a0the\u00a0report,\u00a0some\u00a0of\u00a0the\u00a0explosives\u00a0training\u00a0courses\u00a0were\u00a0of\u2010\nfered\u00a0 by\u00a0 private\u00a0 contractors\u00a0 who\u00a0 failed\u00a0 to\u00a0 perform\u00a0 back\u2010\nground\u00a0checks\u2013\u2013possibly\u00a0allowing\u00a0PCC\u00a0members\u00a0to\u00a0register\u00a0\nfor\u00a0the\u00a0course\u00a0without\u00a0the\u00a0knowledge\u00a0of\u00a0the\u00a0S\u00e3o\u00a0Paulo\u00a0police\u00a0\ndepartment.\u00a0Evidence\u00a0of\u00a0a\u00a0poorly\u00a0planned\u00a0explosives\u00a0training\u00a0\ndoes\u00a0not\u00a0demonstrate\u00a0that\u00a0the\u00a0Brazilian\u00a0police\u00a0have\u00a0been\u00a0in\u2010\nfiltrated\u00a0by\u00a0the\u00a0PCC.\u00a0\n    In\u00a0fact,\u00a0Ramos\u2010Braga\u2019s\u00a0own\u00a0evidence\u00a0undermines\u00a0his\u00a0ar\u2010\ngument\u00a0that\u00a0officials\u00a0and\u00a0the\u00a0PCC\u00a0cooperate.\u00a0The\u00a0article\u00a0about\u00a0\nexplosive\u00a0trainings\u00a0discloses\u00a0that\u00a0in\u00a02012\u00a0the\u00a0PCC\u00a0frequently\u00a0\nattacked\u00a0 police\u00a0 forces,\u00a0 and\u00a0 that\u00a0 the\u00a0 two\u00a0 sides\u00a0 committed\u00a0\naround\u00a0200\u00a0\u201crevenge\u00a0killings\u201d\u00a0within\u00a0a\u00a0couple\u00a0months.\u00a0A\u00a02014\u00a0\narticle\u00a0from\u00a0a\u00a0Brazilian\u00a0newspaper\u00a0shows\u00a0that\u00a0Brazilian\u00a0offi\u2010\ncials\u00a0initiated\u00a0a\u00a0new\u00a0operation\u00a0against\u00a0the\u00a0PCC\u00a0and\u00a0detained\u00a0\nmembers\u00a0 attempting\u00a0 to\u00a0 smuggle\u00a0 drugs\u00a0 out\u00a0 of\u00a0 the\u00a0 country.\u00a0\nOther\u00a0reports\u00a0he\u00a0offered\u00a0show\u00a0that\u00a0police\u00a0have\u00a0arrested\u00a0doz\u2010\nens\u00a0 of\u00a0 PCC\u00a0 members\u00a0 and\u00a0 that\u00a0 Brazilian\u00a0 authorities\u00a0 are\u00a0 in\u00a0 a\u00a0\n\u201cbloody\u00a0struggle\u201d\u00a0to\u00a0subvert\u00a0the\u00a0PCC.\u00a0Ramos\u2010Braga\u00a0did\u00a0offer\u00a0\na\u00a0report\u00a0from\u00a0the\u00a0Australian\u00a0government\u00a0showing\u00a0that\u00a0some\u00a0\nBrazilian\u00a0officials\u00a0were\u00a0corrupt\u00a0as\u00a0of\u00a02012;\u00a0police\u00a0officers\u00a0were\u00a0\n\f16\u00a0                                                     No.\u00a017\u20101998\u00a0\n\narrested\u00a0for\u00a0selling\u00a0information\u00a0to\u00a0the\u00a0PCC\u00a0 about\u00a0investiga\u2010\ntions\u00a0 of\u00a0 the\u00a0 gang\u2019s\u00a0 drug\u00a0 trafficking,\u00a0 while\u00a0 other\u00a0 officers\u00a0 ex\u2010\ntracted\u00a0bribes\u00a0from\u00a0the\u00a0PCC\u00a0through\u00a0kidnapping\u00a0and\u00a0abusing\u00a0\nthe\u00a0 family\u00a0 of\u00a0 PCC\u00a0 members.\u00a0 However,\u00a0 the\u00a0 report\u00a0 does\u00a0 not\u00a0\nshow,\u00a0as\u00a0Ramos\u2010Braga\u00a0asserts,\u00a0that\u00a0corrupt\u00a0police\u00a0physically\u00a0\nharmed\u00a0citizens\u00a0to\u00a0assist\u00a0the\u00a0PCC.\u00a0\n    Finally,\u00a0Ramos\u2010Braga\u00a0presents\u00a0news\u00a0articles\u00a0and\u00a0a\u00a0country\u00a0\nreport\u00a0 issued\u00a0 in\u00a0 2013\u00a0 by\u00a0 the\u00a0 U.S.\u00a0 Department\u00a0 of\u00a0 State\u00a0 that,\u00a0\ntaken\u00a0together,\u00a0show\u00a0that\u00a0police\u00a0o\ufb03cers\u00a0in\u00a0Brazil\u00a0\u201croutinely\u201d\u00a0\nkill\u00a0criminal\u00a0suspects,\u00a0targeting\u00a0men\u00a0from\u00a0the\u00a0\u201cslums.\u201d\u00a0These\u00a0\nreports\u00a0 do\u00a0 not\u00a0 suggest\u00a0 police\u00a0 complicity\u00a0 with\u00a0 the\u00a0 PCC;\u00a0 Ra\u2010\nmos\u2010Braga\u00a0introduces\u00a0them\u00a0to\u00a0show\u00a0that\u00a0the\u00a0police\u00a0may\u00a0target\u00a0\nhim\u00a0because\u00a0he\u00a0is\u00a0from\u00a0the\u00a0slums,\u00a0and\u00a0police\u00a0in\u00a0his\u00a0hometown\u00a0\nmay\u00a0attack\u00a0him\u00a0for\u00a0resembling\u00a0his\u00a0father,\u00a0a\u00a0criminal.\u00a0But\u00a0re\u2010\nports\u00a0that\u00a0police\u00a0o\ufb03cers\u00a0target\u00a0men\u00a0from\u00a0the\u00a0slums\u00a0generally\u00a0\nis\u00a0not\u00a0evidence\u00a0that\u00a0they\u00a0would\u00a0torture\u00a0Ramos\u2010Braga\u00a0specifi\u2010\ncally.\u00a0See\u00a0Orellana\u2010Arias,\u00a0865\u00a0F.3d\u00a0at\u00a0490\u00a0(concluding\u00a0that\u00a0coun\u2010\ntry\u00a0reports\u00a0of\u00a0government\u2019s\u00a0acquiescence\u00a0to\u00a0violence\u00a0against\u00a0\ncitizens\u00a0was\u00a0not\u00a0evidence\u00a0that\u00a0government\u00a0would\u00a0acquiesce\u00a0\nto\u00a0torture\u00a0of\u00a0petitioner\u00a0specifically);\u00a0Lopez,\u00a0810\u00a0F.3d\u00a0at\u00a0493\u00a0(de\u2010\nciding\u00a0that\u00a0petitioner,\u00a0a\u00a0gay\u00a0man,\u00a0did\u00a0not\u00a0show\u00a0threat\u00a0of\u00a0vio\u2010\nlence\u00a0specific\u00a0to\u00a0him\u00a0by\u00a0submitting\u00a0reports\u00a0that\u00a0gay\u00a0men\u00a0have\u00a0\nbeen\u00a0 victims\u00a0 of\u00a0 violence);\u00a0 Rashiah\u00a0 v.\u00a0Ashcroft,\u00a0 388\u00a0 F.3d\u00a0 1126,\u00a0\n1133\u00a0(7th\u00a0Cir.\u00a02004)\u00a0(concluding\u00a0that\u00a0CAT\u00a0relief\u00a0was\u00a0unavaila\u2010\nble\u00a0 to\u00a0 applicant\u00a0 who\u00a0 o\ufb00ered\u00a0 country\u00a0 report\u00a0 describing\u00a0 in\u2010\nstances\u00a0of\u00a0torture\u00a0but\u00a0no\u00a0evidence\u00a0that\u00a0he\u00a0would\u00a0be\u00a0specifi\u2010\ncally\u00a0targeted).\u00a0Twenty\u00a0years\u00a0ago\u00a0police\u00a0o\ufb03cers\u00a0knew\u00a0Ramos\u2010\nBraga\u00a0lived\u00a0in\u00a0the\u00a0slums\u00a0and\u00a0suspected\u00a0he\u00a0was\u00a0a\u00a0criminal,\u00a0but\u00a0\nthere\u00a0is\u00a0no\u00a0evidence\u00a0that\u00a0these\u00a0o\ufb03cers\u00a0remain\u00a0with\u00a0the\u00a0force\u00a0\nor\u00a0that\u00a0they\u00a0would\u00a0recognize\u00a0him\u00a0today.\u00a0\u00a0\n\fNo.\u00a017\u20101998\u00a0                                                         17\u00a0\n\n    In\u00a0sum,\u00a0Ramos\u2010Braga\u2019s\u00a0past\u00a0experiences\u00a0are\u00a0troubling,\u00a0but\u00a0\nhis\u00a0evidence\u00a0does\u00a0not\u00a0compel\u00a0the\u00a0conclusion\u00a0that\u00a0Brazilian\u00a0of\u2010\nficials\u00a0today\u00a0would\u00a0torture\u00a0him\u00a0or\u00a0permit\u00a0the\u00a0PCC\u00a0to\u00a0do\u00a0so.\u00a0\nThus\u00a0we\u00a0will\u00a0not\u00a0disturb\u00a0the\u00a0Board\u2019s\u00a0conclusion\u00a0that\u00a0Ramos\u2010\nBraga\u00a0 o\ufb00ered\u00a0 insu\ufb03cient\u00a0 evidence\u00a0 of\u00a0 o\ufb03cial\u00a0 acquiescence.\u00a0\nAnd\u00a0because\u00a0Ramos\u2010Braga\u2019s\u00a0evidence\u00a0is\u00a0insu\ufb03cient,\u00a0he\u00a0was\u00a0\nnot\u00a0prejudiced\u00a0by\u00a0any\u00a0possible\u00a0attorney\u00a0error\u00a0in\u00a0the\u00a0appeal\u00a0of\u00a0\nhis\u00a0CAT\u00a0application.\u00a0The\u00a0Board\u00a0therefore\u00a0did\u00a0not\u00a0abuse\u00a0its\u00a0dis\u2010\ncretion\u00a0in\u00a0deciding\u00a0that\u00a0equitable\u00a0tolling\u00a0did\u00a0not\u00a0apply\u00a0to\u00a0Ra\u2010\nmos\u2010Braga\u2019s\u00a0second\u00a0motion\u00a0to\u00a0reopen.\u00a0 \u00a0\n      B. Changed\u00a0Conditions\u00a0\n    Ramos\u2010Braga\u00a0 also\u00a0 contends\u00a0 that\u00a0 changed\u00a0 conditions\u00a0 in\u00a0\nBrazil\u00a0warrant\u00a0reopening\u00a0his\u00a0applications\u00a0for\u00a0withholding\u00a0of\u00a0\nremoval.\u00a03\u00a0No\u00a0time\u00a0or\u00a0numeric\u00a0limits\u00a0apply\u00a0to\u00a0a\u00a0motion\u00a0to\u00a0re\u2010\nopen\u00a0 that\u00a0 is\u00a0 based\u00a0 on\u00a0 \u201cchanged\u00a0 circumstances\u00a0 arising\u00a0 \u2026\u00a0 in\u00a0\nthe\u00a0country\u00a0to\u00a0which\u00a0deportation\u00a0has\u00a0been\u00a0ordered.\u201d\u00a08\u00a0C.F.R.\u00a0\n\u00a7\u00a01003.2(c)(3)(ii).\u00a0 For\u00a0 this\u00a0 exception\u00a0 to\u00a0 apply,\u00a0 Ramos\u2010Braga\u00a0\nneeds\u00a0evidence\u00a0of\u00a0a\u00a0changed\u00a0country\u00a0condition\u00a0that\u00a0is\u00a0\u201cmate\u2010\nrial\u00a0and\u00a0was\u00a0not\u00a0available\u00a0and\u00a0could\u00a0not\u00a0have\u00a0been\u00a0discovered\u00a0\nor\u00a0 presented\u201d\u00a0 at\u00a0 the\u00a0 removal\u00a0 hearing.\u00a0 See\u00a0 id.;\u00a0 Ji\u00a0 Cheng\u00a0 Ni,\u00a0\n715\u00a0F.3d\u00a0at\u00a0623.\u00a0This\u00a0court\u2019s\u00a0task\u00a0is\u00a0to\u00a0determine\u00a0whether\u00a0the\u00a0\nBoard\u00a0abused\u00a0its\u00a0discretion\u00a0in\u00a0deciding\u00a0that\u00a0changed\u00a0country\u00a0\nconditions\u00a0do\u00a0not\u00a0excuse\u00a0the\u00a0limits\u00a0on\u00a0Ramos\u2010Braga\u2019s\u00a0motion\u00a0\n\n\n\n\u00a0\u00a0\u00a0\u00a0\u00a0\u00a0\u00a0\u00a0\u00a0\u00a0\u00a0\u00a0\u00a0\u00a0\u00a0\u00a0\u00a0\u00a0\u00a0\u00a0\u00a0\u00a0\u00a0\u00a0\u00a0\u00a0\u00a0\u00a0\u00a0\u00a0\u00a0\u00a0\u00a0\u00a0\u00a0\u00a0\u00a0\u00a0\u00a0\u00a0\u00a0\u00a0\u00a0\u00a0\u00a0\u00a0\u00a0\u00a0\u00a0\n3\u00a0Ramos\u2010Braga\u00a0also\u00a0incorporates\u00a0into\u00a0his\u00a0withholding\u00a0arguments\u00a0his\u00a0view\u00a0\n\nthat\u00a0changed\u00a0conditions\u00a0in\u00a0Brazil\u00a0warrant\u00a0reopening\u00a0proceedings\u00a0so\u00a0that\u00a0\nhe\u00a0can\u00a0apply\u00a0for\u00a0asylum.\u00a0But\u00a0the\u00a0Board\u00a0never\u00a0had\u00a0an\u00a0opportunity\u00a0to\u00a0con\u2010\nsider\u00a0arguments\u00a0related\u00a0to\u00a0asylum\u00a0because\u00a0Ramos\u2010Braga\u00a0did\u00a0not\u00a0develop\u00a0\nthem\u00a0in\u00a0his\u00a0motion\u00a0to\u00a0reopen\u00a0at\u00a0issue\u00a0here.\u00a0We\u00a0therefore\u00a0express\u00a0no\u00a0opin\u2010\nion\u00a0on\u00a0this\u00a0portion\u00a0of\u00a0his\u00a0petition.\u00a0\n\f18\u00a0                                                    No.\u00a017\u20101998\u00a0\n\nto\u00a0 reopen.\u00a0 See\u00a0 Kebe\u00a0 v.\u00a0 Gonzales,\u00a0 473\u00a0F.3d\u00a0 855,\u00a0 857\u00a0 (7th\u00a0Cir.\u00a0\n2007).\u00a0We\u00a0conclude\u00a0that\u00a0the\u00a0Board\u00a0did\u00a0not\u00a0abuse\u00a0its\u00a0discretion.\u00a0\u00a0\n    To\u00a0show\u00a0that\u00a0conditions\u00a0in\u00a0Brazil\u00a0have\u00a0changed,\u00a0Ramos\u2010\nBraga\u00a0offered\u00a0evidence\u00a0that:\u00a0(1)\u00a0the\u00a0PCC\u00a0has\u00a0\u201cmarked\u201d\u00a0him\u00a0to\u00a0\ndie\u00a0 because\u00a0 the\u00a0 gang\u2019s\u00a0 leader\u00a0 believes\u00a0 his\u00a0 brother\u00a0 and\u00a0 two\u00a0\ncousins\u00a0were\u00a0killed\u00a0by\u00a0Ramos\u2010Braga\u2019s\u00a0father\u00a0in\u00a01997;\u00a0(2)\u00a0the\u00a0\nPCC\u00a0 has\u00a0 \u201cbarbarically\u00a0 murdered\u201d\u00a0 eight\u00a0 of\u00a0 Ramos\u2010Braga\u2019s\u00a0\ncousins,\u00a0most\u00a0recently\u00a0in\u00a02013;\u00a0(3)\u00a0the\u00a0PCC\u00a0has\u00a0offered\u00a0a\u00a0re\u2010\nward\u00a0 for\u00a0 Ramos\u2010Braga\u2019s\u00a0 whereabouts;\u00a0 (4)\u00a0 after\u00a0 the\u00a0 PCC\u00a0\nlearned\u00a0that\u00a0Ramos\u2010Braga\u00a0might\u00a0return\u00a0to\u00a0Brazil,\u00a0they\u00a0robbed\u00a0\nhis\u00a0grandfather\u00a0at\u00a0home\u00a0using\u00a0a\u00a0gun\u00a0in\u00a02015\u00a0and\u00a0threatened\u00a0\nhis\u00a0mother\u00a0over\u00a0the\u00a0internet\u00a0in\u00a02016;\u00a0(5)\u00a0one\u00a0police\u00a0district\u00a0re\u2010\nferred\u00a0his\u00a0mother\u2019s\u00a0request\u00a0to\u00a0investigate\u00a0the\u00a02016\u00a0threats,\u00a0and\u00a0\nthe\u00a0other\u00a0district\u00a0promised\u00a0to\u00a0investigate\u00a0the\u00a0threats,\u00a0but\u00a0the\u00a0\ninvestigation\u00a0has\u00a0not\u00a0been\u00a0resolved;\u00a0and\u00a0(6)\u00a0Brazilian\u00a0police\u00a0\nhave\u00a0routinely\u00a0committed\u00a0extrajudicial\u00a0killings\u00a0of\u00a0men\u00a0from\u00a0\nthe\u00a0slums\u00a0whom\u00a0they\u00a0suspect\u00a0to\u00a0be\u00a0criminals.\u00a0\u00a0\n       1.\u00a0     Withholding\u00a0under\u00a0CAT\u00a0\u00a0\n    Pertaining\u00a0 to\u00a0 his\u00a0 CAT\u00a0 application,\u00a0 Ramos\u2010Braga\u00a0 argues\u00a0\nthat\u00a0the\u00a0PCC\u2019s\u00a0recent\u00a0growth\u00a0and\u00a0threats\u00a0are\u00a0a\u00a0changed\u00a0con\u2010\ndition\u00a0that\u00a0the\u00a0Board\u00a0\u201cirrationally\u201d\u00a0discounted\u00a0as\u00a0a\u00a0\u201ccontinu\u2010\nation\u201d\u00a0of\u00a0dangers\u00a0that\u00a0he\u00a0previously\u00a0experienced\u00a0in\u00a0Brazil.\u00a0He\u00a0\nrelies\u00a0on\u00a0an\u00a0out\u2010of\u2010circuit\u00a0decision,\u00a0Malty\u00a0v.\u00a0Ashcroft,\u00a0381\u00a0F.3d\u00a0\n942\u00a0(9th\u00a0Cir.\u00a02004),\u00a0in\u00a0which\u00a0the\u00a0Ninth\u00a0Circuit\u00a0said\u00a0\u201cchanged\u00a0\ncircumstances\u00a0 will\u00a0 almost\u00a0 always\u00a0 relate\u00a0 to\u00a0 [an]\u00a0 initial\u00a0\nclaim\u00a0\u2026\u00a0.\u00a0 The\u00a0 critical\u00a0 question\u00a0 is\u00a0 \u2026\u00a0 whether\u00a0 circumstances\u00a0\nhave\u00a0 changed\u00a0 su\ufb03ciently\u00a0 that\u00a0 a\u00a0 petitioner\u00a0 who\u00a0 previously\u00a0\ndid\u00a0not\u00a0have\u00a0a\u00a0legitimate\u00a0claim\u00a0\u2026\u00a0now\u00a0has\u00a0a\u00a0well\u2010founded\u201d\u00a0\nclaim.\u00a0Id.\u00a0at\u00a0945.\u00a0A\u00a0worsening\u00a0PCC\u00a0threat\u00a0is,\u00a0however,\u00a0imma\u2010\nterial\u00a0to\u00a0whether\u00a0Ramos\u2010Braga\u2019s\u00a0CAT\u00a0application\u00a0must\u00a0be\u00a0re\u2010\n\fNo.\u00a017\u20101998\u00a0                                                         19\u00a0\n\nopened.\u00a0As\u00a0discussed\u00a0above,\u00a0he\u00a0needed\u00a0but\u00a0failed\u00a0to\u00a0o\ufb00er\u00a0ev\u2010\nidence\u00a0that\u00a0compels\u00a0finding\u00a0that\u00a0Brazilian\u00a0o\ufb03cials\u00a0would\u00a0ac\u2010\nquiesce\u00a0to\u00a0his\u00a0torture\u00a0by\u00a0the\u00a0PCC.\u00a0\n    Ramos\u2010Braga\u00a0also\u00a0argues\u00a0that\u00a0the\u00a0Board\u00a0ignored\u00a0new\u00a0evi\u2010\ndence\u00a0that\u00a0he\u00a0would\u00a0face\u00a0torture\u00a0directly\u00a0from\u00a0public\u00a0officials\u00a0\nif\u00a0he\u00a0is\u00a0removed\u00a0to\u00a0Brazil.\u00a0He\u00a0again\u00a0points\u00a0to\u00a0the\u00a0recent\u00a0news\u00a0\narticles\u00a0 reporting\u00a0 that\u00a0 Brazilian\u00a0 police\u00a0 have\u00a0 targeted\u00a0 men\u00a0\nfrom\u00a0 the\u00a0 slums\u00a0 and\u00a0 criminal\u00a0 suspects\u00a0 for\u00a0 extrajudicial\u00a0 kill\u2010\nings.\u00a0He\u00a0stresses\u00a0that\u00a0police\u00a0in\u00a0his\u00a0hometown\u00a0beat\u00a0him,\u00a0possi\u2010\nbly\u00a0 suspecting\u00a0 he\u00a0 was\u00a0 a\u00a0 criminal\u00a0 because\u00a0 he\u00a0 lived\u00a0 in\u00a0 the\u00a0\nslums.\u00a0He\u00a0says\u00a0that\u00a0his\u00a0evidence,\u00a0together,\u00a0establishes\u00a0a\u00a0sub\u2010\nstantial\u00a0 likelihood\u00a0 that\u00a0 police\u00a0 officers\u00a0 will\u00a0 torture\u00a0 him.\u00a0 The\u00a0\nBoard,\u00a0while\u00a0considering\u00a0Ramos\u2010Braga\u2019s\u00a0argument\u00a0for\u00a0equi\u2010\ntable\u00a0tolling,\u00a0said\u00a0that\u00a0the\u00a0evidence\u00a0he\u00a0offered\u2014initially\u00a0and\u00a0\nwith\u00a0his\u00a0second\u00a0motion\u00a0to\u00a0reopen\u2014did\u00a0not\u00a0show\u00a0that\u00a0officials\u00a0\nwere\u00a0more\u00a0likely\u00a0than\u00a0not\u00a0to\u00a0torture\u00a0him.\u00a0\u00a0\n    We\u00a0 will\u00a0 reverse\u00a0 the\u00a0 Board\u2019s\u00a0 conclusion\u00a0 that\u00a0 Ramos\u2010\nBraga\u2019s\u00a0evidence\u00a0is\u00a0insufficient\u00a0only\u00a0if\u00a0the\u00a0evidence\u00a0compels\u00a0a\u00a0\ncontrary\u00a0 conclusion.\u00a0 See\u00a0Lopez,\u00a0 810\u00a0 F.3d\u00a0 at\u00a0 492\u201393.\u00a0 As\u00a0 ex\u2010\nplained\u00a0above,\u00a0the\u00a0articles\u00a0Ramos\u2010Braga\u00a0recently\u00a0offered\u00a0do\u00a0\nnot\u00a0compel\u00a0the\u00a0conclusion\u00a0that\u00a0public\u00a0officials\u00a0are\u00a0more\u00a0likely\u00a0\nthan\u00a0not\u00a0to\u00a0torture\u00a0him.\u00a0We\u00a0have\u00a0said\u00a0that\u00a0reports\u00a0that\u00a0officials\u00a0\nhave\u00a0tortured\u00a0members\u00a0of\u00a0a\u00a0certain\u00a0group\u00a0do\u00a0not\u00a0necessarily\u00a0\ndemonstrate\u00a0 that\u00a0 a\u00a0 petitioner\u00a0 who\u00a0 belongs\u00a0 to\u00a0 that\u00a0 group\u00a0\nwould\u00a0face\u00a0a\u00a0substantial\u00a0risk\u00a0of\u00a0torture\u00a0if\u00a0removed.\u00a0Bernard\u00a0v.\u00a0\nSessions,\u00a0881\u00a0F.3d\u00a01042,\u00a01047\u201348\u00a0(7th\u00a0Cir.\u00a02018).\u00a0To\u00a0show\u00a0a\u00a0risk\u00a0\nspecific\u00a0to\u00a0him,\u00a0Ramos\u2010Braga\u00a0needed\u00a0evidence\u00a0that\u00a0Brazilian\u00a0\npolice\u00a0would\u00a0recognize\u00a0him\u00a0as\u00a0part\u00a0of\u00a0the\u00a0groups\u00a0targeted\u00a0for\u00a0\ntorture.\u00a0 See\u00a0Lopez,\u00a0 810\u00a0 F.3d\u00a0 at\u00a0 493;\u00a0 Rashiah,\u00a0 388\u00a0F.3d\u00a0 at\u00a0 1133.\u00a0\nYet\u00a0he\u00a0offered\u00a0no\u00a0evidence\u00a0that\u00a0Brazilian\u00a0police\u00a0today\u00a0would\u00a0\nsuspect\u00a0him\u00a0of\u00a0crime\u00a0or\u00a0would\u00a0know,\u00a0roughly\u00a0twenty\u00a0years\u00a0\n\f20\u00a0                                                      No.\u00a017\u20101998\u00a0\n\nlater,\u00a0that\u00a0he\u00a0lived\u00a0in\u00a0the\u00a0slums\u00a0in\u00a01998.\u00a0To\u00a0the\u00a0extent\u00a0he\u00a0fears\u00a0\npolice\u00a0torture\u00a0because\u00a0he\u00a0would\u00a0be\u00a0forced\u00a0to\u00a0live\u00a0in\u00a0the\u00a0slums\u00a0\nif\u00a0removed\u00a0to\u00a0Brazil,\u00a0this\u00a0fear\u00a0of\u00a0generalized\u00a0violence\u00a0is\u00a0insuf\u2010\nficient\u00a0to\u00a0establish\u00a0that\u00a0he\u00a0in\u00a0particular\u00a0is\u00a0more\u00a0likely\u00a0than\u00a0not\u00a0\nto\u00a0be\u00a0tortured.\u00a0See\u00a0Lozano\u2010Zuniga\u00a0v.\u00a0Lynch,\u00a0832\u00a0F.3d\u00a0822,\u00a0830\u2013\n31\u00a0(7th\u00a0Cir.\u00a02016).\u00a0\n    Because\u00a0Ramos\u2010Braga\u00a0did\u00a0not\u00a0present\u00a0evidence\u00a0that\u00a0con\u2010\nditions\u00a0in\u00a0Brazil\u00a0have\u00a0changed\u00a0such\u00a0that\u00a0he\u00a0now\u00a0may\u00a0have\u00a0a\u00a0\nCAT\u00a0claim,\u00a0the\u00a0Board\u00a0did\u00a0not\u00a0abuse\u00a0its\u00a0discretion\u00a0in\u00a0denying\u00a0\nhis\u00a0motion\u00a0to\u00a0reopen\u00a0proceedings\u00a0on\u00a0that\u00a0form\u00a0of\u00a0relief.\u00a0\u00a0\n       2.\u00a0     Withholding\u00a0under\u00a0Statute\u00a0\n    Ramos\u2010Braga\u00a0next\u00a0argues\u00a0that\u00a0changed\u00a0conditions\u00a0in\u00a0Bra\u2010\nzil\u00a0excuse\u00a0the\u00a0limits\u00a0on\u00a0his\u00a0motion\u00a0to\u00a0reopen\u00a0his\u00a0application\u00a0\nfor\u00a0withholding\u00a0under\u00a0statute,\u00a0but\u00a0again\u00a0he\u00a0is\u00a0wrong.\u00a0He\u00a0first\u00a0\npoints\u00a0to\u00a0new\u00a0evidence\u00a0that\u00a0the\u00a0PCC\u2019s\u00a0intent\u00a0to\u00a0kill\u00a0him\u00a0stems\u00a0\nfrom\u00a0 the\u00a0 gang\u00a0 leader\u2019s\u00a0 desire\u00a0 to\u00a0 avenge\u00a0 the\u00a0 murders\u00a0 of\u00a0 his\u00a0\nfamily\u00a0 members.\u00a0 But\u00a0 this\u00a0 motive\u00a0 has\u00a0 not\u00a0 changed\u00a0 since\u00a0 the\u00a0\nkillings\u00a0 of\u00a0 the\u00a0 gang\u00a0 leader\u2019s\u00a0 family\u00a0 in\u00a0 1997,\u00a0 well\u00a0 before\u00a0 the\u00a0\n2014\u00a0 removal\u00a0 hearing,\u00a0 and\u00a0 thus\u00a0 the\u00a0 motivation,\u00a0 though\u00a0 re\u2010\ncently\u00a0discovered,\u00a0is\u00a0not\u00a0a\u00a0changed\u00a0condition.\u00a0\u00a0\n    Second,\u00a0Ramos\u2010Braga\u00a0argues\u00a0that\u00a0the\u00a0PCC\u2019s\u00a0o\ufb00er\u00a0of\u00a0a\u00a0re\u2010\nward\u00a0for\u00a0his\u00a0whereabouts\u00a0is\u00a0a\u00a0changed\u00a0condition,\u00a0but\u00a0he\u00a0has\u00a0\nnot\u00a0carried\u00a0his\u00a0evidentiary\u00a0burden.\u00a0To\u00a0show\u00a0that\u00a0the\u00a0reward\u00a0\no\ufb00er\u00a0is\u00a0a\u00a0changed\u00a0condition,\u00a0Ramos\u2010Braga\u00a0needed\u00a0evidence\u00a0\nthat\u00a0 the\u00a0 o\ufb00er\u00a0 was\u00a0 made\u00a0 after\u00a0 the\u00a0 removal\u00a0 hearing.\u00a0 See\u00a0 Xiu\u00a0\nZhen\u00a0Lin\u00a0v.\u00a0Mukasey,\u00a0532\u00a0F.3d\u00a0596,\u00a0596\u201397\u00a0(7th\u00a0Cir.\u00a02008).\u00a0In\u00a0his\u00a0\npetition\u00a0he\u00a0sidesteps\u00a0his\u00a0burden\u00a0and\u00a0contends\u00a0the\u00a0Board\u00a0spec\u2010\nulated\u00a0that\u00a0the\u00a0reward\u00a0o\ufb00er\u00a0might\u00a0date\u00a0back\u00a0to\u00a01998.\u00a0But\u00a0that\u00a0\nis\u00a0not\u00a0what\u00a0the\u00a0Board\u00a0said;\u00a0it\u00a0observed\u00a0that\u00a0the\u00a0gang\u2019s\u00a0intent\u00a0\nto\u00a0 harm\u00a0 him\u00a0 dated\u00a0 that\u00a0 far\u00a0 back\u00a0 and\u00a0 said\u00a0 that\u00a0 no\u00a0 evidence,\u00a0\n\fNo.\u00a017\u20101998\u00a0                                                      21\u00a0\n\nincluding\u00a0 an\u00a0 a\ufb03davit\u00a0 from\u00a0 his\u00a0 mother\u2019s\u00a0 neighbor\u00a0 who\u00a0 re\u2010\nported\u00a0the\u00a0reward\u00a0o\ufb00er,\u00a0showed\u00a0the\u00a0o\ufb00er\u00a0was\u00a0made\u00a0after\u00a0the\u00a0\nremoval\u00a0hearing.\u00a0Instead\u00a0of\u00a0clarifying\u00a0when\u00a0the\u00a0reward\u00a0was\u00a0\no\ufb00ered,\u00a0 Ramos\u2010Braga\u00a0 says\u00a0 that\u00a0 the\u00a0 o\ufb00er\u00a0 could\u00a0 not\u00a0 be\u00a0 from\u00a0\n1998\u00a0because\u00a0the\u00a0neighbor\u00a0learned\u00a0of\u00a0it\u00a0through\u00a0her\u00a019\u2010year\u2010\nold\u00a0son,\u00a0a\u00a0current\u00a0PCC\u00a0member\u00a0who\u00a0would\u00a0have\u00a0been\u00a0an\u00a0in\u2010\nfant\u00a0 then.\u00a0 But\u00a0 this\u00a0 reasoning\u00a0 is\u00a0 flawed;\u00a0 the\u00a0 o\ufb00er\u00a0 may\u00a0 have\u00a0\nbeen\u00a0old\u00a0when\u00a0the\u00a0neighbor\u2019s\u00a0son\u00a0learned\u00a0of\u00a0it.\u00a0As\u00a0di\ufb03cult\u00a0as\u00a0\nit\u00a0might\u00a0have\u00a0been\u00a0for\u00a0Ramos\u2010Braga\u00a0to\u00a0gather\u00a0evidence\u00a0while\u00a0\ndetained,\u00a0he\u00a0has\u00a0never\u00a0represented\u00a0that\u00a0he\u00a0exhaustively\u00a0inves\u2010\ntigated\u00a0when\u00a0this\u00a0o\ufb00er\u00a0was\u00a0made.\u00a0\n    Last,\u00a0 Ramos\u2010Braga\u00a0 disputes\u00a0 the\u00a0 Board\u2019s\u00a0 conclusion\u00a0 that\u00a0\nrecent\u00a0dangers\u00a0posed\u00a0by\u00a0the\u00a0PCC\u00a0are\u00a0a\u00a0continuation\u00a0of\u00a0condi\u2010\ntions\u00a0that\u00a0existed\u00a0before\u00a0the\u00a0removal\u00a0hearing.\u00a0Although\u00a0wors\u2010\nening\u00a0conditions\u00a0in\u00a0the\u00a0country\u00a0of\u00a0removal\u00a0may\u00a0constitute\u00a0a\u00a0\nchange\u00a0that\u00a0requires\u00a0reopening,\u00a0see\u00a0id.;\u00a0Ji\u00a0Cheng\u00a0Ni,\u00a0715\u00a0F.3d\u00a0\nat\u00a0627;\u00a0 Mekhael\u00a0v.\u00a0 Mukasey,\u00a0509\u00a0 F.3d\u00a0 326,\u00a0327\u00a0(7th\u00a0Cir.\u00a02007),\u00a0\nthe\u00a0PCC\u2019s\u00a0recent\u00a0threats,\u00a0robbery,\u00a0and\u00a0murders\u00a0are\u00a0immate\u2010\nrial\u00a0 to\u00a0 whether\u00a0 Ramos\u2010Braga\u2019s\u00a0 application\u00a0 for\u00a0 withholding\u00a0\nunder\u00a0statute\u00a0should\u00a0be\u00a0reopened.\u00a0The\u00a0IJ\u00a0denied\u00a0this\u00a0applica\u2010\ntion\u00a0not\u00a0for\u00a0lack\u00a0of\u00a0evidence\u00a0of\u00a0past\u00a0persecution,\u00a0but\u00a0because\u00a0\nRamos\u2010Braga\u00a0did\u00a0not\u00a0establish\u00a0a\u00a0nexus\u00a0between\u00a0his\u00a0likely\u00a0per\u2010\nsecution\u00a0by\u00a0the\u00a0PCC\u00a0and\u00a0his\u00a0particular\u00a0social\u00a0group.\u00a0Thus\u00a0to\u00a0\npresent\u00a0evidence\u00a0that\u00a0conditions\u00a0have\u00a0degenerated\u00a0so\u00a0that\u00a0he\u00a0\nnow\u00a0has\u00a0a\u00a0claim\u00a0for\u00a0withholding\u00a0under\u00a0statute,\u00a0Ramos\u2010Braga\u00a0\nneeded\u00a0 to\u00a0 show\u00a0 a\u00a0 change\u00a0 related\u00a0 to\u00a0 this\u00a0 nexus\u00a0 between\u00a0 the\u00a0\nPCC\u2019s\u00a0 persecution\u00a0 and\u00a0 his\u00a0 social\u00a0 group\u00a0 based\u00a0 on\u00a0 ties\u00a0 to\u00a0 his\u00a0\nfather.\u00a0He\u00a0did\u00a0present\u00a0newly\u00a0found\u00a0evidence\u00a0of\u00a0the\u00a0PCC\u2019s\u00a0mo\u2010\ntive\u00a0for\u00a0harming\u00a0him,\u00a0but\u00a0again,\u00a0that\u00a0motive\u00a0has\u00a0not\u00a0changed\u00a0\nsince\u00a01997.\u00a0\u00a0\n\f22\u00a0                                                    No.\u00a017\u20101998\u00a0\n\n   In\u00a0 sum,\u00a0 Ramos\u2010Braga\u00a0 failed\u00a0 to\u00a0 o\ufb00er\u00a0 new,\u00a0 material\u00a0 evi\u2010\ndence\u00a0 that\u00a0 conditions\u00a0 in\u00a0 Brazil\u00a0 have\u00a0 changed\u00a0 since\u00a0 the\u00a0 re\u2010\nmoval\u00a0hearing.\u00a0\u00a0\n                                III.\u00a0\n    The\u00a0Board\u00a0did\u00a0not\u00a0abuse\u00a0its\u00a0discretion\u00a0by\u00a0denying\u00a0Ramos\u2010\nBraga\u2019s\u00a0second\u00a0motion\u00a0to\u00a0reopen\u00a0as\u00a0numerically\u00a0barred\u00a0and\u00a0\nuntimely.\u00a0 Ramos\u2010Braga\u00a0 neither\u00a0 experienced\u00a0 prejudice\u00a0 from\u00a0\nhis\u00a0former\u00a0attorney\u2019s\u00a0potential\u00a0errors\u00a0nor\u00a0presented\u00a0new,\u00a0ma\u2010\nterial\u00a0 evidence\u00a0 that\u00a0 conditions\u00a0 in\u00a0 Brazil\u00a0 have\u00a0 changed\u00a0 since\u00a0\nthe\u00a0removal\u00a0hearing.\u00a0Accordingly,\u00a0the\u00a0petition\u00a0for\u00a0review\u00a0is\u00a0\u00a0\n                                                         DENIED.\u00a0\n\f",
            "ocr": false,
            "opinion_id": 4303820
        }
    ],
    "court_short_name": "Seventh Circuit",
    "court_full_name": "Court of Appeals for the Seventh Circuit",
    "court_type": "F",
    "court_jurisdiction": "USA, Federal",
    "crime_category": "Robbery"
}